{
  "page": {
    "url": "https://rheolab.site/",
    "status_code": 200,
    "redirect_chain": [],
    "headers": {
      "Date": "Sun, 12 Apr 2026 02:30:09 GMT",
      "Server": "Apache/2.4.58 (Ubuntu)",
      "Strict-Transport-Security": "max-age=31536000; includeSubDomains; preload",
      "X-Frame-Options": "DENY",
      "X-Content-Type-Options": "nosniff",
      "Referrer-Policy": "strict-origin-when-cross-origin",
      "Permissions-Policy": "accelerometer=(), autoplay=(), camera=(), geolocation=(), gyroscope=(), magnetometer=(), microphone=(), payment=(), usb=(), browsing-topics=()",
      "Content-Security-Policy": "default-src 'self'; base-uri 'self'; object-src 'none'; frame-ancestors 'none'; form-action 'self'; img-src 'self' data: https:; style-src 'self' 'unsafe-inline' https://fonts.googleapis.com; font-src 'self' data: https://fonts.gstatic.com; script-src 'self' 'unsafe-inline'; connect-src 'self' https://license.vizbuka.ru; upgrade-insecure-requests",
      "Last-Modified": "Sun, 12 Apr 2026 02:27:27 GMT",
      "ETag": "\"1e8a4-64f3a1b6c6b02-gzip\"",
      "Accept-Ranges": "bytes",
      "Vary": "Accept-Encoding",
      "Content-Encoding": "gzip",
      "Content-Length": "31653",
      "Keep-Alive": "timeout=5, max=100",
      "Connection": "Keep-Alive",
      "Content-Type": "text/html"
    },
    "meta_tags": {
      "viewport": "width=device-width, initial-scale=1.0",
      "description": "RheoLab Enterprise \u00e2\u0080\u0094 \u00d0\u00bf\u00d1\u0080\u00d0\u00be\u00d0\u00b3\u00d1\u0080\u00d0\u00b0\u00d0\u00bc\u00d0\u00bc\u00d0\u00b0 \u00d0\u00b4\u00d0\u00bb\u00d1\u008f \u00d1\u0085\u00d1\u0080\u00d0\u00b0\u00d0\u00bd\u00d0\u00b5\u00d0\u00bd\u00d0\u00b8\u00d1\u008f, \u00d1\u0081\u00d1\u0080\u00d0\u00b0\u00d0\u00b2\u00d0\u00bd\u00d0\u00b5\u00d0\u00bd\u00d0\u00b8\u00d1\u008f \u00d0\u00b8 \u00d0\u00bf\u00d0\u00be\u00d0\u00b4\u00d0\u00b3\u00d0\u00be\u00d1\u0082\u00d0\u00be\u00d0\u00b2\u00d0\u00ba\u00d0\u00b8 \u00d0\u00be\u00d1\u0082\u00d1\u0087\u00d1\u0091\u00d1\u0082\u00d0\u00be\u00d0\u00b2 \u00d0\u00bf\u00d0\u00be \u00d1\u0080\u00d0\u00b5\u00d0\u00b7\u00d1\u0083\u00d0\u00bb\u00d1\u008c\u00d1\u0082\u00d0\u00b0\u00d1\u0082\u00d0\u00b0\u00d0\u00bc \u00d1\u0080\u00d0\u00b5\u00d0\u00be\u00d0\u00bb\u00d0\u00be\u00d0\u00b3\u00d0\u00b8\u00d1\u0087\u00d0\u00b5\u00d1\u0081\u00d0\u00ba\u00d0\u00b8\u00d1\u0085 \u00d1\u008d\u00d0\u00ba\u00d1\u0081\u00d0\u00bf\u00d0\u00b5\u00d1\u0080\u00d0\u00b8\u00d0\u00bc\u00d0\u00b5\u00d0\u00bd\u00d1\u0082\u00d0\u00be\u00d0\u00b2 \u00d1\u0081 \u00d1\u0080\u00d0\u00b0\u00d0\u00b7\u00d0\u00bd\u00d1\u008b\u00d1\u0085 \u00d0\u00bf\u00d1\u0080\u00d0\u00b8\u00d0\u00b1\u00d0\u00be\u00d1\u0080\u00d0\u00be\u00d0\u00b2.",
      "keywords": "\u00d1\u0080\u00d0\u00b5\u00d0\u00be\u00d0\u00bb\u00d0\u00be\u00d0\u00b3\u00d0\u00b8\u00d1\u008f, \u00d1\u0080\u00d0\u00b5\u00d0\u00b7\u00d1\u0083\u00d0\u00bb\u00d1\u008c\u00d1\u0082\u00d0\u00b0\u00d1\u0082\u00d1\u008b \u00d1\u008d\u00d0\u00ba\u00d1\u0081\u00d0\u00bf\u00d0\u00b5\u00d1\u0080\u00d0\u00b8\u00d0\u00bc\u00d0\u00b5\u00d0\u00bd\u00d1\u0082\u00d0\u00be\u00d0\u00b2, \u00d0\u00b1\u00d0\u00b8\u00d0\u00b1\u00d0\u00bb\u00d0\u00b8\u00d0\u00be\u00d1\u0082\u00d0\u00b5\u00d0\u00ba\u00d0\u00b0 \u00d0\u00b4\u00d0\u00b0\u00d0\u00bd\u00d0\u00bd\u00d1\u008b\u00d1\u0085, \u00d0\u00bb\u00d0\u00b0\u00d0\u00b1\u00d0\u00be\u00d1\u0080\u00d0\u00b0\u00d1\u0082\u00d0\u00be\u00d1\u0080\u00d0\u00bd\u00d1\u008b\u00d0\u00b5 \u00d0\u00b4\u00d0\u00b0\u00d0\u00bd\u00d0\u00bd\u00d1\u008b\u00d0\u00b5, Grace, Chandler, Fann, BSL, Brookfield, RheoLab, \u00d1\u0081\u00d1\u0080\u00d0\u00b0\u00d0\u00b2\u00d0\u00bd\u00d0\u00b5\u00d0\u00bd\u00d0\u00b8\u00d0\u00b5 \u00d1\u0081\u00d0\u00b5\u00d1\u0080\u00d0\u00b8\u00d0\u00b9, \u00d0\u00be\u00d1\u0082\u00d1\u0087\u00d1\u0091\u00d1\u0082\u00d1\u008b",
      "author": "RheoLab",
      "robots": "index, follow",
      "theme-color": "#081120",
      "og:title": "RheoLab Enterprise \u00e2\u0080\u0094 \u00d0\u0098\u00d0\u00bd\u00d1\u0081\u00d1\u0082\u00d1\u0080\u00d1\u0083\u00d0\u00bc\u00d0\u00b5\u00d0\u00bd\u00d1\u0082 \u00d0\u00b4\u00d0\u00bb\u00d1\u008f \u00d1\u0080\u00d0\u00b0\u00d0\u00b1\u00d0\u00be\u00d1\u0082\u00d1\u008b \u00d1\u0081 \u00d1\u0080\u00d0\u00b5\u00d0\u00be\u00d0\u00bb\u00d0\u00be\u00d0\u00b3\u00d0\u00b8\u00d1\u0087\u00d0\u00b5\u00d1\u0081\u00d0\u00ba\u00d0\u00b8\u00d0\u00bc\u00d0\u00b8 \u00d0\u00b4\u00d0\u00b0\u00d0\u00bd\u00d0\u00bd\u00d1\u008b\u00d0\u00bc\u00d0\u00b8",
      "og:description": "RheoLab Enterprise \u00e2\u0080\u0094 \u00d0\u00bf\u00d1\u0080\u00d0\u00be\u00d0\u00b3\u00d1\u0080\u00d0\u00b0\u00d0\u00bc\u00d0\u00bc\u00d0\u00b0 \u00d0\u00b4\u00d0\u00bb\u00d1\u008f \u00d1\u0085\u00d1\u0080\u00d0\u00b0\u00d0\u00bd\u00d0\u00b5\u00d0\u00bd\u00d0\u00b8\u00d1\u008f, \u00d1\u0081\u00d1\u0080\u00d0\u00b0\u00d0\u00b2\u00d0\u00bd\u00d0\u00b5\u00d0\u00bd\u00d0\u00b8\u00d1\u008f \u00d0\u00b8 \u00d0\u00bf\u00d0\u00be\u00d0\u00b4\u00d0\u00b3\u00d0\u00be\u00d1\u0082\u00d0\u00be\u00d0\u00b2\u00d0\u00ba\u00d0\u00b8 \u00d0\u00be\u00d1\u0082\u00d1\u0087\u00d1\u0091\u00d1\u0082\u00d0\u00be\u00d0\u00b2 \u00d0\u00bf\u00d0\u00be \u00d1\u0080\u00d0\u00b5\u00d0\u00b7\u00d1\u0083\u00d0\u00bb\u00d1\u008c\u00d1\u0082\u00d0\u00b0\u00d1\u0082\u00d0\u00b0\u00d0\u00bc \u00d1\u0080\u00d0\u00b5\u00d0\u00be\u00d0\u00bb\u00d0\u00be\u00d0\u00b3\u00d0\u00b8\u00d1\u0087\u00d0\u00b5\u00d1\u0081\u00d0\u00ba\u00d0\u00b8\u00d1\u0085 \u00d1\u008d\u00d0\u00ba\u00d1\u0081\u00d0\u00bf\u00d0\u00b5\u00d1\u0080\u00d0\u00b8\u00d0\u00bc\u00d0\u00b5\u00d0\u00bd\u00d1\u0082\u00d0\u00be\u00d0\u00b2 \u00d1\u0081 \u00d1\u0080\u00d0\u00b0\u00d0\u00b7\u00d0\u00bd\u00d1\u008b\u00d1\u0085 \u00d0\u00bf\u00d1\u0080\u00d0\u00b8\u00d0\u00b1\u00d0\u00be\u00d1\u0080\u00d0\u00be\u00d0\u00b2.",
      "og:type": "website",
      "og:url": "https://rheolab.site/",
      "og:locale": "ru_RU",
      "og:site_name": "RheoLab Enterprise",
      "og:image": "https://rheolab.site/og-image.svg",
      "twitter:card": "summary_large_image",
      "twitter:title": "RheoLab Enterprise \u00e2\u0080\u0094 \u00d0\u0098\u00d0\u00bd\u00d1\u0081\u00d1\u0082\u00d1\u0080\u00d1\u0083\u00d0\u00bc\u00d0\u00b5\u00d0\u00bd\u00d1\u0082 \u00d0\u00b4\u00d0\u00bb\u00d1\u008f \u00d1\u0080\u00d0\u00b0\u00d0\u00b1\u00d0\u00be\u00d1\u0082\u00d1\u008b \u00d1\u0081 \u00d1\u0080\u00d0\u00b5\u00d0\u00be\u00d0\u00bb\u00d0\u00be\u00d0\u00b3\u00d0\u00b8\u00d1\u0087\u00d0\u00b5\u00d1\u0081\u00d0\u00ba\u00d0\u00b8\u00d0\u00bc\u00d0\u00b8 \u00d0\u00b4\u00d0\u00b0\u00d0\u00bd\u00d0\u00bd\u00d1\u008b\u00d0\u00bc\u00d0\u00b8",
      "twitter:description": "RheoLab Enterprise \u00e2\u0080\u0094 \u00d0\u00bf\u00d1\u0080\u00d0\u00be\u00d0\u00b3\u00d1\u0080\u00d0\u00b0\u00d0\u00bc\u00d0\u00bc\u00d0\u00b0 \u00d0\u00b4\u00d0\u00bb\u00d1\u008f \u00d1\u0085\u00d1\u0080\u00d0\u00b0\u00d0\u00bd\u00d0\u00b5\u00d0\u00bd\u00d0\u00b8\u00d1\u008f, \u00d1\u0081\u00d1\u0080\u00d0\u00b0\u00d0\u00b2\u00d0\u00bd\u00d0\u00b5\u00d0\u00bd\u00d0\u00b8\u00d1\u008f \u00d0\u00b8 \u00d0\u00bf\u00d0\u00be\u00d0\u00b4\u00d0\u00b3\u00d0\u00be\u00d1\u0082\u00d0\u00be\u00d0\u00b2\u00d0\u00ba\u00d0\u00b8 \u00d0\u00be\u00d1\u0082\u00d1\u0087\u00d1\u0091\u00d1\u0082\u00d0\u00be\u00d0\u00b2 \u00d0\u00bf\u00d0\u00be \u00d1\u0080\u00d0\u00b5\u00d0\u00b7\u00d1\u0083\u00d0\u00bb\u00d1\u008c\u00d1\u0082\u00d0\u00b0\u00d1\u0082\u00d0\u00b0\u00d0\u00bc \u00d1\u0080\u00d0\u00b5\u00d0\u00be\u00d0\u00bb\u00d0\u00be\u00d0\u00b3\u00d0\u00b8\u00d1\u0087\u00d0\u00b5\u00d1\u0081\u00d0\u00ba\u00d0\u00b8\u00d1\u0085 \u00d1\u008d\u00d0\u00ba\u00d1\u0081\u00d0\u00bf\u00d0\u00b5\u00d1\u0080\u00d0\u00b8\u00d0\u00bc\u00d0\u00b5\u00d0\u00bd\u00d1\u0082\u00d0\u00be\u00d0\u00b2 \u00d1\u0081 \u00d1\u0080\u00d0\u00b0\u00d0\u00b7\u00d0\u00bd\u00d1\u008b\u00d1\u0085 \u00d0\u00bf\u00d1\u0080\u00d0\u00b8\u00d0\u00b1\u00d0\u00be\u00d1\u0080\u00d0\u00be\u00d0\u00b2.",
      "twitter:image": "https://rheolab.site/og-image.svg"
    },
    "title": "RheoLab Enterprise \u00e2\u0080\u0094 \u00d0\u0098\u00d0\u00bd\u00d1\u0081\u00d1\u0082\u00d1\u0080\u00d1\u0083\u00d0\u00bc\u00d0\u00b5\u00d0\u00bd\u00d1\u0082 \u00d0\u00b4\u00d0\u00bb\u00d1\u008f \u00d1\u0080\u00d0\u00b0\u00d0\u00b1\u00d0\u00be\u00d1\u0082\u00d1\u008b \u00d1\u0081 \u00d1\u0080\u00d0\u00b5\u00d0\u00be\u00d0\u00bb\u00d0\u00be\u00d0\u00b3\u00d0\u00b8\u00d1\u0087\u00d0\u00b5\u00d1\u0081\u00d0\u00ba\u00d0\u00b8\u00d0\u00bc\u00d0\u00b8 \u00d0\u00b4\u00d0\u00b0\u00d0\u00bd\u00d0\u00bd\u00d1\u008b\u00d0\u00bc\u00d0\u00b8",
    "description": "RheoLab Enterprise \u00e2\u0080\u0094 \u00d0\u00bf\u00d1\u0080\u00d0\u00be\u00d0\u00b3\u00d1\u0080\u00d0\u00b0\u00d0\u00bc\u00d0\u00bc\u00d0\u00b0 \u00d0\u00b4\u00d0\u00bb\u00d1\u008f \u00d1\u0085\u00d1\u0080\u00d0\u00b0\u00d0\u00bd\u00d0\u00b5\u00d0\u00bd\u00d0\u00b8\u00d1\u008f, \u00d1\u0081\u00d1\u0080\u00d0\u00b0\u00d0\u00b2\u00d0\u00bd\u00d0\u00b5\u00d0\u00bd\u00d0\u00b8\u00d1\u008f \u00d0\u00b8 \u00d0\u00bf\u00d0\u00be\u00d0\u00b4\u00d0\u00b3\u00d0\u00be\u00d1\u0082\u00d0\u00be\u00d0\u00b2\u00d0\u00ba\u00d0\u00b8 \u00d0\u00be\u00d1\u0082\u00d1\u0087\u00d1\u0091\u00d1\u0082\u00d0\u00be\u00d0\u00b2 \u00d0\u00bf\u00d0\u00be \u00d1\u0080\u00d0\u00b5\u00d0\u00b7\u00d1\u0083\u00d0\u00bb\u00d1\u008c\u00d1\u0082\u00d0\u00b0\u00d1\u0082\u00d0\u00b0\u00d0\u00bc \u00d1\u0080\u00d0\u00b5\u00d0\u00be\u00d0\u00bb\u00d0\u00be\u00d0\u00b3\u00d0\u00b8\u00d1\u0087\u00d0\u00b5\u00d1\u0081\u00d0\u00ba\u00d0\u00b8\u00d1\u0085 \u00d1\u008d\u00d0\u00ba\u00d1\u0081\u00d0\u00bf\u00d0\u00b5\u00d1\u0080\u00d0\u00b8\u00d0\u00bc\u00d0\u00b5\u00d0\u00bd\u00d1\u0082\u00d0\u00be\u00d0\u00b2 \u00d1\u0081 \u00d1\u0080\u00d0\u00b0\u00d0\u00b7\u00d0\u00bd\u00d1\u008b\u00d1\u0085 \u00d0\u00bf\u00d1\u0080\u00d0\u00b8\u00d0\u00b1\u00d0\u00be\u00d1\u0080\u00d0\u00be\u00d0\u00b2.",
    "canonical": "https://rheolab.site/",
    "h1_tags": [
      "\u00d0\u00a3\u00d0\u00bd\u00d0\u00b8\u00d1\u0084\u00d0\u00b8\u00d0\u00ba\u00d0\u00b0\u00d1\u0086\u00d0\u00b8\u00d1\u008f, \u00d1\u0085\u00d1\u0080\u00d0\u00b0\u00d0\u00bd\u00d0\u00b5\u00d0\u00bd\u00d0\u00b8\u00d0\u00b5\u00d0\u00b8 \u00d0\u00b0\u00d0\u00bd\u00d0\u00b0\u00d0\u00bb\u00d0\u00b8\u00d0\u00b7 \u00d1\u0080\u00d0\u00b5\u00d0\u00b7\u00d1\u0083\u00d0\u00bb\u00d1\u008c\u00d1\u0082\u00d0\u00b0\u00d1\u0082\u00d0\u00be\u00d0\u00b2\u00d1\u008d\u00d0\u00ba\u00d1\u0081\u00d0\u00bf\u00d0\u00b5\u00d1\u0080\u00d0\u00b8\u00d0\u00bc\u00d0\u00b5\u00d0\u00bd\u00d1\u0082\u00d0\u00be\u00d0\u00b2"
    ],
    "heading_structure": [
      {
        "level": 1,
        "text": "\u00d0\u00a3\u00d0\u00bd\u00d0\u00b8\u00d1\u0084\u00d0\u00b8\u00d0\u00ba\u00d0\u00b0\u00d1\u0086\u00d0\u00b8\u00d1\u008f, \u00d1\u0085\u00d1\u0080\u00d0\u00b0\u00d0\u00bd\u00d0\u00b5\u00d0\u00bd\u00d0\u00b8\u00d0\u00b5\u00d0\u00b8 \u00d0\u00b0\u00d0\u00bd\u00d0\u00b0\u00d0\u00bb\u00d0\u00b8\u00d0\u00b7 \u00d1\u0080\u00d0\u00b5\u00d0\u00b7\u00d1\u0083\u00d0\u00bb\u00d1\u008c\u00d1\u0082\u00d0\u00b0\u00d1\u0082\u00d0\u00be\u00d0\u00b2\u00d1\u008d\u00d0\u00ba\u00d1\u0081\u00d0\u00bf\u00d0\u00b5\u00d1\u0080\u00d0\u00b8\u00d0\u00bc\u00d0\u00b5\u00d0\u00bd\u00d1\u0082\u00d0\u00be\u00d0\u00b2"
      },
      {
        "level": 2,
        "text": "\u00d0\u0097\u00d0\u00bd\u00d0\u00b0\u00d0\u00ba\u00d0\u00be\u00d0\u00bc\u00d1\u008b\u00d0\u00b5 \u00d0\u00bf\u00d1\u0080\u00d0\u00be\u00d0\u00b1\u00d0\u00bb\u00d0\u00b5\u00d0\u00bc\u00d1\u008b"
      },
      {
        "level": 2,
        "text": "\u00d0\u009e\u00d1\u0082 \u00d0\u00b8\u00d0\u00bc\u00d0\u00bf\u00d0\u00be\u00d1\u0080\u00d1\u0082\u00d0\u00b0 \u00d0\u00b4\u00d0\u00be \u00d0\u00b3\u00d0\u00be\u00d1\u0082\u00d0\u00be\u00d0\u00b2\u00d0\u00be\u00d0\u00b3\u00d0\u00be \u00d0\u00be\u00d1\u0082\u00d1\u0087\u00d1\u0091\u00d1\u0082\u00d0\u00b0"
      },
      {
        "level": 2,
        "text": "\u00d0\u009f\u00d0\u00be\u00d1\u0081\u00d0\u00bc\u00d0\u00be\u00d1\u0082\u00d1\u0080\u00d0\u00b8\u00d1\u0082\u00d0\u00b5, \u00d0\u00ba\u00d0\u00b0\u00d0\u00ba \u00d1\u008d\u00d1\u0082\u00d0\u00be \u00d1\u0080\u00d0\u00b0\u00d0\u00b1\u00d0\u00be\u00d1\u0082\u00d0\u00b0\u00d0\u00b5\u00d1\u0082"
      },
      {
        "level": 2,
        "text": "\u00d0\u009a\u00d0\u00be\u00d0\u00bc\u00d1\u0083 \u00d1\u008d\u00d1\u0082\u00d0\u00be \u00d0\u00b4\u00d0\u00b5\u00d0\u00b9\u00d1\u0081\u00d1\u0082\u00d0\u00b2\u00d0\u00b8\u00d1\u0082\u00d0\u00b5\u00d0\u00bb\u00d1\u008c\u00d0\u00bd\u00d0\u00be \u00d0\u00bd\u00d1\u0083\u00d0\u00b6\u00d0\u00bd\u00d0\u00be"
      },
      {
        "level": 2,
        "text": "\u00d0\u00a1\u00d0\u00b2\u00d1\u008f\u00d0\u00b7\u00d0\u00b0\u00d1\u0082\u00d1\u008c\u00d1\u0081\u00d1\u008f \u00d1\u0081 \u00d0\u00ba\u00d0\u00be\u00d0\u00bc\u00d0\u00b0\u00d0\u00bd\u00d0\u00b4\u00d0\u00be\u00d0\u00b9"
      },
      {
        "level": 3,
        "text": "\u00d0\u0093\u00d0\u00b4\u00d0\u00b5 \u00d1\u0082\u00d0\u00be\u00d1\u0082 \u00d1\u0084\u00d0\u00b0\u00d0\u00b9\u00d0\u00bb \u00d0\u00b7\u00d0\u00b0 \u00d0\u00bf\u00d1\u0080\u00d0\u00be\u00d1\u0088\u00d0\u00bb\u00d1\u008b\u00d0\u00b9 \u00d0\u00b3\u00d0\u00be\u00d0\u00b4?"
      },
      {
        "level": 3,
        "text": "\u00d0\u00a3 \u00d0\u00ba\u00d0\u00b0\u00d0\u00b6\u00d0\u00b4\u00d0\u00be\u00d0\u00b3\u00d0\u00be \u00d0\u00bf\u00d1\u0080\u00d0\u00b8\u00d0\u00b1\u00d0\u00be\u00d1\u0080\u00d0\u00b0 \u00d1\u0081\u00d0\u00b2\u00d0\u00be\u00d0\u00b9 \u00d1\u0084\u00d0\u00be\u00d1\u0080\u00d0\u00bc\u00d0\u00b0\u00d1\u0082"
      },
      {
        "level": 3,
        "text": "\u00d0\u0092\u00d0\u00b5\u00d1\u0081\u00d1\u008c \u00d0\u00b4\u00d0\u00b5\u00d0\u00bd\u00d1\u008c \u00d0\u00b2 Excel \u00e2\u0080\u0094 \u00d1\u008d\u00d1\u0082\u00d0\u00be \u00d0\u00bd\u00d0\u00b5 \u00d0\u00b0\u00d0\u00bd\u00d0\u00b0\u00d0\u00bb\u00d0\u00b8\u00d0\u00b7"
      },
      {
        "level": 3,
        "text": "\u00d0\u009e\u00d1\u0082\u00d0\u00ba\u00d1\u0080\u00d1\u008b\u00d0\u00bb \u00e2\u0080\u0094 \u00d0\u00bf\u00d0\u00be\u00d1\u0081\u00d0\u00bc\u00d0\u00be\u00d1\u0082\u00d1\u0080\u00d0\u00b5\u00d0\u00bb \u00e2\u0080\u0094 \u00d0\u00bf\u00d0\u00be\u00d1\u0082\u00d0\u00b5\u00d1\u0080\u00d1\u008f\u00d0\u00bb"
      },
      {
        "level": 3,
        "text": "\u00d0\u0090\u00d0\u00b2\u00d1\u0082\u00d0\u00be\u00d0\u00bc\u00d0\u00b0\u00d1\u0082\u00d0\u00b8\u00d1\u0087\u00d0\u00b5\u00d1\u0081\u00d0\u00ba\u00d0\u00b8\u00d0\u00b9 \u00d0\u00b8\u00d0\u00bc\u00d0\u00bf\u00d0\u00be\u00d1\u0080\u00d1\u0082"
      },
      {
        "level": 3,
        "text": "\u00d0\u009c\u00d0\u00b0\u00d1\u0082\u00d0\u00b5\u00d0\u00bc\u00d0\u00b0\u00d1\u0082\u00d0\u00b8\u00d0\u00ba\u00d0\u00b0 \u00d0\u00b1\u00d0\u00b5\u00d0\u00b7 \u00d0\u00be\u00d1\u0088\u00d0\u00b8\u00d0\u00b1\u00d0\u00be\u00d0\u00ba"
      },
      {
        "level": 3,
        "text": "\u00d0\u00a1\u00d1\u0080\u00d0\u00b0\u00d0\u00b2\u00d0\u00bd\u00d0\u00b5\u00d0\u00bd\u00d0\u00b8\u00d0\u00b5 \u00d0\u00b8 \u00d0\u00b1\u00d1\u0080\u00d0\u00b5\u00d0\u00bd\u00d0\u00b4\u00d0\u00b8\u00d1\u0080\u00d0\u00be\u00d0\u00b2\u00d0\u00b0\u00d0\u00bd\u00d0\u00bd\u00d1\u008b\u00d0\u00b5 \u00d0\u00be\u00d1\u0082\u00d1\u0087\u00d1\u0091\u00d1\u0082\u00d1\u008b"
      },
      {
        "level": 3,
        "text": "\u00d0\u009d\u00d0\u00b5\u00d1\u0084\u00d1\u0082\u00d0\u00b5\u00d1\u0081\u00d0\u00b5\u00d1\u0080\u00d0\u00b2\u00d0\u00b8\u00d1\u0081\u00d0\u00bd\u00d1\u008b\u00d0\u00b5 \u00d0\u00ba\u00d0\u00be\u00d0\u00bc\u00d0\u00bf\u00d0\u00b0\u00d0\u00bd\u00d0\u00b8\u00d0\u00b8"
      },
      {
        "level": 3,
        "text": "\u00d0\u009d\u00d0\u0098\u00d0\u0098 \u00d0\u00b8 \u00d0\u00bd\u00d0\u00b0\u00d1\u0083\u00d1\u0087\u00d0\u00bd\u00d1\u008b\u00d0\u00b5 \u00d1\u0086\u00d0\u00b5\u00d0\u00bd\u00d1\u0082\u00d1\u0080\u00d1\u008b"
      },
      {
        "level": 3,
        "text": "\u00d0\u009d\u00d0\u00b5\u00d1\u0084\u00d1\u0082\u00d0\u00b5\u00d0\u00b4\u00d0\u00be\u00d0\u00b1\u00d1\u008b\u00d0\u00b2\u00d0\u00b0\u00d1\u008e\u00d1\u0089\u00d0\u00b8\u00d0\u00b5 \u00d0\u00ba\u00d0\u00be\u00d0\u00bc\u00d0\u00bf\u00d0\u00b0\u00d0\u00bd\u00d0\u00b8\u00d0\u00b8"
      },
      {
        "level": 3,
        "text": "\u00d0\u009f\u00d1\u0080\u00d0\u00be\u00d0\u00b8\u00d0\u00b7\u00d0\u00b2\u00d0\u00be\u00d0\u00b4\u00d0\u00b8\u00d1\u0082\u00d0\u00b5\u00d0\u00bb\u00d0\u00b8 \u00d1\u0080\u00d0\u00b5\u00d0\u00b0\u00d0\u00b3\u00d0\u00b5\u00d0\u00bd\u00d1\u0082\u00d0\u00be\u00d0\u00b2"
      },
      {
        "level": 4,
        "text": "\u00d0\u009f\u00d1\u0080\u00d0\u00be\u00d0\u00b4\u00d1\u0083\u00d0\u00ba\u00d1\u0082"
      },
      {
        "level": 4,
        "text": "\u00d0\u00a1\u00d0\u00b2\u00d1\u008f\u00d0\u00b7\u00d1\u008c"
      },
      {
        "level": 4,
        "text": "\u00d0\u009f\u00d1\u0080\u00d0\u00b0\u00d0\u00b2\u00d0\u00be\u00d0\u00b2\u00d0\u00b0\u00d1\u008f \u00d0\u00b8\u00d0\u00bd\u00d1\u0084\u00d0\u00be\u00d1\u0080\u00d0\u00bc\u00d0\u00b0\u00d1\u0086\u00d0\u00b8\u00d1\u008f"
      }
    ],
    "word_count": 756,
    "text_content": "RheoLab Enterprise \u00e2\u0080\u0094 \u00d0\u0098\u00d0\u00bd\u00d1\u0081\u00d1\u0082\u00d1\u0080\u00d1\u0083\u00d0\u00bc\u00d0\u00b5\u00d0\u00bd\u00d1\u0082 \u00d0\u00b4\u00d0\u00bb\u00d1\u008f \u00d1\u0080\u00d0\u00b0\u00d0\u00b1\u00d0\u00be\u00d1\u0082\u00d1\u008b \u00d1\u0081 \u00d1\u0080\u00d0\u00b5\u00d0\u00be\u00d0\u00bb\u00d0\u00be\u00d0\u00b3\u00d0\u00b8\u00d1\u0087\u00d0\u00b5\u00d1\u0081\u00d0\u00ba\u00d0\u00b8\u00d0\u00bc\u00d0\u00b8 \u00d0\u00b4\u00d0\u00b0\u00d0\u00bd\u00d0\u00bd\u00d1\u008b\u00d0\u00bc\u00d0\u00b8 \u00d0\u009f\u00d0\u00b5\u00d1\u0080\u00d0\u00b5\u00d0\u00b9\u00d1\u0082\u00d0\u00b8 \u00d0\u00ba \u00d1\u0081\u00d0\u00be\u00d0\u00b4\u00d0\u00b5\u00d1\u0080\u00d0\u00b6\u00d0\u00b8\u00d0\u00bc\u00d0\u00be\u00d0\u00bc\u00d1\u0083 \u00d0\u0091\u00d0\u00b5\u00d1\u0081\u00d0\u00bf\u00d0\u00bb\u00d0\u00b0\u00d1\u0082\u00d0\u00bd\u00d0\u00be \u00e2\u0080\u0094 30 \u00d0\u00b4\u00d0\u00bd\u00d0\u00b5\u00d0\u00b9, \u00d0\u00b2\u00d0\u00b5\u00d1\u0081\u00d1\u008c \u00d1\u0084\u00d1\u0083\u00d0\u00bd\u00d0\u00ba\u00d1\u0086\u00d0\u00b8\u00d0\u00be\u00d0\u00bd\u00d0\u00b0\u00d0\u00bb \u00d0\u00a3\u00d0\u00bd\u00d0\u00b8\u00d1\u0084\u00d0\u00b8\u00d0\u00ba\u00d0\u00b0\u00d1\u0086\u00d0\u00b8\u00d1\u008f, \u00d1\u0085\u00d1\u0080\u00d0\u00b0\u00d0\u00bd\u00d0\u00b5\u00d0\u00bd\u00d0\u00b8\u00d0\u00b5 \u00d0\u00b8 \u00d0\u00b0\u00d0\u00bd\u00d0\u00b0\u00d0\u00bb\u00d0\u00b8\u00d0\u00b7 \u00d1\u0080\u00d0\u00b5\u00d0\u00b7\u00d1\u0083\u00d0\u00bb\u00d1\u008c\u00d1\u0082\u00d0\u00b0\u00d1\u0082\u00d0\u00be\u00d0\u00b2 \u00d1\u008d\u00d0\u00ba\u00d1\u0081\u00d0\u00bf\u00d0\u00b5\u00d1\u0080\u00d0\u00b8\u00d0\u00bc\u00d0\u00b5\u00d0\u00bd\u00d1\u0082\u00d0\u00be\u00d0\u00b2 \u00d0\u00a0\u00d0\u00b0\u00d0\u00b7\u00d0\u00bd\u00d1\u008b\u00d0\u00b5 \u00d0\u00bf\u00d1\u0080\u00d0\u00b8\u00d0\u00b1\u00d0\u00be\u00d1\u0080\u00d1\u008b \u00e2\u0080\u0094 \u00d1\u0080\u00d0\u00b0\u00d0\u00b7\u00d0\u00bd\u00d1\u008b\u00d0\u00b5 \u00d1\u0084\u00d0\u00be\u00d1\u0080\u00d0\u00bc\u00d0\u00b0\u00d1\u0082\u00d1\u008b. RheoLab \u00d0\u00bf\u00d1\u0080\u00d0\u00b8\u00d0\u00bd\u00d0\u00b8\u00d0\u00bc\u00d0\u00b0\u00d0\u00b5\u00d1\u0082 \u00d1\u0084\u00d0\u00b0\u00d0\u00b9\u00d0\u00bb\u00d1\u008b\n        Grace, Chandler, Fann, Ofite, BSL-R1 \u00d0\u00b8 Brookfield,\n        \u00d0\u00bf\u00d1\u0080\u00d0\u00b8\u00d0\u00b2\u00d0\u00be\u00d0\u00b4\u00d0\u00b8\u00d1\u0082 \u00d0\u00b8\u00d1\u0085 \u00d0\u00ba \u00d0\u00b5\u00d0\u00b4\u00d0\u00b8\u00d0\u00bd\u00d0\u00be\u00d0\u00bc\u00d1\u0083 \u00d1\u0084\u00d0\u00be\u00d1\u0080\u00d0\u00bc\u00d0\u00b0\u00d1\u0082\u00d1\u0083 ,\n        \u00d1\u0080\u00d0\u00b0\u00d1\u0081\u00d1\u0081\u00d1\u0087\u00d0\u00b8\u00d1\u0082\u00d1\u008b\u00d0\u00b2\u00d0\u00b0\u00d0\u00b5\u00d1\u0082 \u00d1\u0080\u00d0\u00b5\u00d0\u00be\u00d0\u00bb\u00d0\u00be\u00d0\u00b3\u00d0\u00b8\u00d1\u0087\u00d0\u00b5\u00d1\u0081\u00d0\u00ba\u00d0\u00b8\u00d0\u00b5 \u00d0\u00bc\u00d0\u00be\u00d0\u00b4\u00d0\u00b5\u00d0\u00bb\u00d0\u00b8 \u00d0\u00b8 \u00d1\u0081\u00d0\u00be\u00d1\u0085\u00d1\u0080\u00d0\u00b0\u00d0\u00bd\u00d1\u008f\u00d0\u00b5\u00d1\u0082 \u00d0\u00ba\u00d0\u00b0\u00d0\u00b6\u00d0\u00b4\u00d1\u008b\u00d0\u00b9 \u00d0\u00be\u00d0\u00bf\u00d1\u008b\u00d1\u0082 \u00d0\u00b2 \u00d0\u00be\u00d0\u00b1\u00d1\u0089\u00d0\u00b5\u00d0\u00b9 \u00d0\u00b1\u00d0\u00b8\u00d0\u00b1\u00d0\u00bb\u00d0\u00b8\u00d0\u00be\u00d1\u0082\u00d0\u00b5\u00d0\u00ba\u00d0\u00b5 .\n        \u00d0\u0092\u00d1\u0081\u00d0\u00b5 \u00d0\u00b4\u00d0\u00b0\u00d0\u00bd\u00d0\u00bd\u00d1\u008b\u00d0\u00b5 \u00d0\u00b2 \u00d0\u00be\u00d0\u00b4\u00d0\u00bd\u00d0\u00be\u00d0\u00bc \u00d0\u00bc\u00d0\u00b5\u00d1\u0081\u00d1\u0082\u00d0\u00b5 \u00e2\u0080\u0094 \u00d0\u00ba\u00d0\u00be\u00d1\u0080\u00d1\u0080\u00d0\u00b5\u00d0\u00ba\u00d1\u0082\u00d0\u00bd\u00d0\u00be \u00d1\u0081\u00d1\u0080\u00d0\u00b0\u00d0\u00b2\u00d0\u00bd\u00d0\u00b8\u00d0\u00bc\u00d1\u008b\u00d0\u00b5,\n        \u00d1\u0081 \u00d0\u00b3\u00d0\u00be\u00d1\u0082\u00d0\u00be\u00d0\u00b2\u00d1\u008b\u00d0\u00bc \u00d0\u00be\u00d1\u0082\u00d1\u0087\u00d1\u0091\u00d1\u0082\u00d0\u00be\u00d0\u00bc . \u00d0\u00a1\u00d0\u00ba\u00d0\u00b0\u00d1\u0087\u00d0\u00b0\u00d1\u0082\u00d1\u008c \u00d0\u00b1\u00d0\u00b5\u00d1\u0081\u00d0\u00bf\u00d0\u00bb\u00d0\u00b0\u00d1\u0082\u00d0\u00bd\u00d0\u00be \u00d0\u00b4\u00d0\u00bb\u00d1\u008f Windows \u00d0\u009d\u00d0\u00b0\u00d0\u00bf\u00d0\u00b8\u00d1\u0081\u00d0\u00b0\u00d1\u0082\u00d1\u008c \u00d0\u00bd\u00d0\u00b0\u00d0\u00bc \u00d0\u009e\u00d1\u0082 \u00d0\u00b8\u00d0\u00bd\u00d0\u00b6\u00d0\u00b5\u00d0\u00bd\u00d0\u00b5\u00d1\u0080\u00d0\u00be\u00d0\u00b2, \u00d1\u0081\u00d0\u00be\u00d0\u00b7\u00d0\u00b4\u00d0\u00b0\u00d0\u00b2\u00d1\u0088\u00d0\u00b8\u00d1 BSL-R1 \u00e2\u0080\u0094 \u00d0\u00bf\u00d0\u00b5\u00d1\u0080\u00d0\u00b2\u00d1\u008b\u00d0\u00b9 \u00d1\u0080\u00d0\u00be\u00d1\u0081\u00d1\u0081\u00d0\u00b8\u00d0\u00b9\u00d1\u0081\u00d0\u00ba\u00d0\u00b8\u00d0\u00b9 \u00d0\u00bb\u00d0\u00b0\u00d0\u00b1\u00d0\u00be\u00d1\u0080\u00d0\u00b0\u00d1\u0082\u00d0\u00be\u00d1\u0080\u00d0\u00bd\u00d1\u008b\u00d0\u00b9 \u00d1\u0080\u00d0\u00b5\u00d0\u00be\u00d0\u00bc\u00d0\u00b5\u00d1\u0082\u00d1\u0080 \u00d0\u0090\u00d0\u00bd\u00d0\u00b0\u00d0\u00bb\u00d0\u00b8\u00d0\u00b7 \u00d0\u0091\u00d0\u00b8\u00d0\u00b1\u00d0\u00bb\u00d0\u00b8\u00d0\u00be\u00d1\u0082\u00d0\u00b5\u00d0\u00ba\u00d0\u00b0 \u00d0\u00a1\u00d1\u0080\u00d0\u00b0\u00d0\u00b2\u00d0\u00bd\u00d0\u00b5\u00d0\u00bd\u00d0\u00b8\u00d0\u00b5 \u00d0\u009e\u00d1\u0082\u00d1\u0087\u00d1\u0091\u00d1\u0082\u00d1\u008b \u00d0\u0093\u00d1\u0080\u00d0\u00b0\u00d1\u0084\u00d0\u00b8\u00d0\u00ba \u00d1\u0080\u00d0\u00b5\u00d0\u00be\u00d0\u00bb\u00d0\u00be\u00d0\u00b3\u00d0\u00b8\u00d1\u0087\u00d0\u00b5\u00d1\u0081\u00d0\u00ba\u00d0\u00b8\u00d1\u0085 \u00d0\u00b4\u00d0\u00b0\u00d0\u00bd\u00d0\u00bd\u00d1\u008b\u00d1 Grace M5600 R1B5 \u00d0\u009c\u00d0\u00b0\u00d0\u00ba\u00d1\u0081. \u00d0\u00b2\u00d1\u008f\u00d0\u00b7\u00d0\u00ba\u00d0\u00be\u00d1\u0081\u00d1\u0082\u00d1\u008c 2986 \u00d1\u0081\u00d0\u009f \u00d0\u00a1\u00d1\u0080. \u00d0\u00b2\u00d1\u008f\u00d0\u00b7\u00d0\u00ba\u00d0\u00be\u00d1\u0081\u00d1\u0082\u00d1\u008c 704 \u00d1\u0081\u00d0\u009f \u00d0\u00a1\u00d1\u0080. \u00d1\u0082\u00d0\u00b5\u00d0\u00bc\u00d0\u00bf\u00d0\u00b5\u00d1\u0080\u00d0\u00b0\u00d1\u0082\u00d1\u0083\u00d1\u0080\u00d0\u00b0 105\u00c2\u00b0C \u00d0\u009c\u00d0\u00b0\u00d0\u00ba\u00d1\u0081. \u00d0\u00b4\u00d0\u00b0\u00d0\u00b2\u00d0\u00bb\u00d0\u00b5\u00d0\u00bd\u00d0\u00b8\u00d0\u00b5 31.5 \u00d0\u00b1\u00d0\u00b0\u00d1\u0080 \u00d0\u0094\u00d0\u00bb\u00d0\u00b8\u00d1\u0082\u00d0\u00b5\u00d0\u00bb\u00d1\u008c\u00d0\u00bd\u00d0\u00be\u00d1\u0081\u00d1\u0082\u00d1\u008c 179 \u00d0\u00bc\u00d0\u00b8\u00d0\u00bd \u00d0\u0092\u00d1\u0080\u00d0\u00b5\u00d0\u00bc\u00d1\u008f (\u00d0\u00bc\u00d0\u00b8\u00d0\u00bd) \u00d0\u0092\u00d1\u008f\u00d0\u00b7\u00d0\u00ba\u00d0\u00be\u00d1\u0081\u00d1\u0082\u00d1\u008c (\u00d1\u0081\u00d0\u009f) / \u00d0\u00a1\u00d0\u00ba\u00d0\u00be\u00d1\u0080. \u00d1\u0081\u00d0\u00b4\u00d0\u00b2\u00d0\u00b8\u00d0\u00b3\u00d0\u00b0 (1/\u00d1\u0081) \u00d0\u00a2\u00d0\u00b5\u00d0\u00bc\u00d0\u00bf\u00d0\u00b5\u00d1\u0080\u00d0\u00b0\u00d1\u0082\u00d1\u0083\u00d1\u0080\u00d0\u00b0 (\u00c2\u00b0C) 10 20 30 40 50 60 70 80 90 100 110 120 130 140 150 160 170 0 200 400 600 800 1,000 1,200 1,400 1,600 1,800 2,000 2,200 2,400 2,600 2,800 3,000 3,200 20 30 40 50 60 70 80 90 100 110 \u00d0\u0092\u00d1\u0080\u00d0\u00b5\u00d0\u00bc\u00d1\u008f: 58.63 \u00d0\u00bc\u00d0\u00b8\u00d0\u00bd \u00d0\u0092\u00d1\u008f\u00d0\u00b7\u00d0\u00ba\u00d0\u00be\u00d1\u0081\u00d1\u0082\u00d1\u008c: 737.9 \u00d1\u0081\u00d0\u009f \u00d0\u00a2\u00d0\u00b5\u00d0\u00bc\u00d0\u00bf\u00d0\u00b5\u00d1\u0080\u00d0\u00b0\u00d1\u0082\u00d1\u0083\u00d1\u0080\u00d0\u00b0: 107.2 \u00c2\u00b0C \u00d0\u00a1\u00d0\u00ba\u00d0\u00be\u00d1\u0080. \u00d1\u0081\u00d0\u00b4\u00d0\u00b2\u00d0\u00b8\u00d0\u00b3\u00d0\u00b0: 100 1/\u00d1\u0081 \u00d0\u0092\u00d1\u008f\u00d0\u00b7\u00d0\u00ba\u00d0\u00be\u00d1\u0081\u00d1\u0082\u00d1\u008c \u00d0\u00a2\u00d0\u00b5\u00d0\u00bc\u00d0\u00bf\u00d0\u00b5\u00d1\u0080\u00d0\u00b0\u00d1\u0082\u00d1\u0083\u00d1\u0080\u00d0\u00b0 \u00d0\u00a1\u00d0\u00ba\u00d0\u00be\u00d1\u0080. \u00d1\u0081\u00d0\u00b4\u00d0\u00b2\u00d0\u00b8\u00d0\u00b3\u00d0\u00b0 \u00d0\u0097\u00d0\u00bd\u00d0\u00b0\u00d0\u00ba\u00d0\u00be\u00d0\u00bc\u00d1\u008b\u00d0\u00b5 \u00d0\u00bf\u00d1\u0080\u00d0\u00be\u00d0\u00b1\u00d0\u00bb\u00d0\u00b5\u00d0\u00bc\u00d1\u008b \u00d0\u00a1 \u00d1\u0087\u00d0\u00b5\u00d0\u00bc \u00d0\u00bc\u00d1\u008b \u00d0\u00bf\u00d1\u0080\u00d0\u00be\u00d1\u0089\u00d0\u00b0\u00d0\u00b5\u00d0\u00bc\u00d1\u0081\u00d1\u008f \u00d0\u00bf\u00d1\u0080\u00d0\u00b8 \u00d0\u00bf\u00d0\u00b5\u00d1\u0080\u00d0\u00b5\u00d1\u0085\u00d0\u00be\u00d0\u00b4\u00d0\u00b5 \u00d0\u00bd\u00d0\u00b0 RheoLab \u00d0\u0093\u00d0\u00b4\u00d0\u00b5 \u00d1\u0082\u00d0\u00be\u00d1\u0082 \u00d1\u0084\u00d0\u00b0\u00d0\u00b9\u00d0\u00bb \u00d0\u00b7\u00d0\u00b0 \u00d0\u00bf\u00d1\u0080\u00d0\u00be\u00d1\u0088\u00d0\u00bb\u00d1\u008b\u00d0\u00b9 \u00d0\u00b3\u00d0\u00be\u00d0\u00b4? \u00d0\u00a0\u00d0\u00b5\u00d0\u00b7\u00d1\u0083\u00d0\u00bb\u00d1\u008c\u00d1\u0082\u00d0\u00b0\u00d1\u0082\u00d1\u008b \u00d1\u008d\u00d0\u00ba\u00d1\u0081\u00d0\u00bf\u00d0\u00b5\u00d1\u0080\u00d0\u00b8\u00d0\u00bc\u00d0\u00b5\u00d0\u00bd\u00d1\u0082\u00d0\u00be\u00d0\u00b2 \u00d1\u0080\u00d0\u00b0\u00d0\u00b7\u00d0\u00b1\u00d1\u0080\u00d0\u00be\u00d1\u0081\u00d0\u00b0\u00d0\u00bd\u00d1\u008b \u00d0\u00bf\u00d0\u00be \u00d0\u00bf\u00d0\u00b0\u00d0\u00bf\u00d0\u00ba\u00d0\u00b0\u00d0\u00bc, \u00d1\u0084\u00d0\u00bb\u00d1\u008d\u00d1\u0088\u00d0\u00ba\u00d0\u00b0\u00d0\u00bc \u00d0\u00b8 \u00d0\u00bf\u00d0\u00be\u00d1\u0087\u00d1\u0082\u00d0\u00b5. \u00d0\u009d\u00d0\u00b0\u00d0\u00b9\u00d1\u0082\u00d0\u00b8 \u00d0\u00bd\u00d1\u0083\u00d0\u00b6\u00d0\u00bd\u00d1\u008b\u00d0\u00b9 \u00d0\u00be\u00d0\u00bf\u00d1\u008b\u00d1\u0082 \u00e2\u0080\u0094 \u00d0\u00b7\u00d0\u00b0\u00d0\u00b4\u00d0\u00b0\u00d1\u0087\u00d0\u00b0 \u00d0\u00bd\u00d0\u00b0 \u00d0\u00bf\u00d0\u00be\u00d0\u00bb\u00d1\u0087\u00d0\u00b0\u00d1\u0081\u00d0\u00b0. \u00d0\u0095\u00d0\u00b4\u00d0\u00b8\u00d0\u00bd\u00d0\u00be\u00d0\u00b5 \u00d0\u00bc\u00d0\u00b5\u00d1\u0081\u00d1\u0082\u00d0\u00be \u00d1\u0085\u00d1\u0080\u00d0\u00b0\u00d0\u00bd\u00d0\u00b5\u00d0\u00bd\u00d0\u00b8\u00d1\u008f, \u00d0\u00bf\u00d0\u00be\u00d0\u00b8\u00d1\u0081\u00d0\u00ba \u00d0\u00b7\u00d0\u00b0 \u00d1\u0081\u00d0\u00b5\u00d0\u00ba\u00d1\u0083\u00d0\u00bd\u00d0\u00b4\u00d1\u008b \u00d0\u00a3 \u00d0\u00ba\u00d0\u00b0\u00d0\u00b6\u00d0\u00b4\u00d0\u00be\u00d0\u00b3\u00d0\u00be \u00d0\u00bf\u00d1\u0080\u00d0\u00b8\u00d0\u00b1\u00d0\u00be\u00d1\u0080\u00d0\u00b0 \u00d1\u0081\u00d0\u00b2\u00d0\u00be\u00d0\u00b9 \u00d1\u0084\u00d0\u00be\u00d1\u0080\u00d0\u00bc\u00d0\u00b0\u00d1\u0082 Grace, Chandler \u00d0\u00b8 Fann \u00d0\u00bd\u00d0\u00b0\u00d0\u00b7\u00d1\u008b\u00d0\u00b2\u00d0\u00b0\u00d1\u008e\u00d1\u0082 \u00d0\u00be\u00d0\u00b4\u00d0\u00bd\u00d0\u00b8 \u00d0\u00b8 \u00d1\u0082\u00d0\u00b5 \u00d0\u00b6\u00d0\u00b5 \u00d0\u00bf\u00d0\u00be\u00d0\u00ba\u00d0\u00b0\u00d0\u00b7\u00d0\u00b0\u00d1\u0082\u00d0\u00b5\u00d0\u00bb\u00d0\u00b8 \u00d0\u00bf\u00d0\u00be-\u00d1\u0080\u00d0\u00b0\u00d0\u00b7\u00d0\u00bd\u00d0\u00be\u00d0\u00bc\u00d1\u0083. \u00d0\u00a1\u00d1\u0080\u00d0\u00b0\u00d0\u00b2\u00d0\u00bd\u00d0\u00b8\u00d1\u0082\u00d1\u008c \u00d0\u00b8\u00d1\u0085 \u00d0\u00bd\u00d0\u00b0\u00d0\u00bf\u00d1\u0080\u00d1\u008f\u00d0\u00bc\u00d1\u0083\u00d1\u008e \u00d0\u00b2 Excel \u00e2\u0080\u0094 \u00d0\u00bc\u00d1\u0083\u00d1\u0087\u00d0\u00b5\u00d0\u00bd\u00d0\u00b8\u00d0\u00b5. \u00d0\u009e\u00d0\u00b4\u00d0\u00b8\u00d0\u00bd\u00d0\u00b0\u00d0\u00ba\u00d0\u00be\u00d0\u00b2\u00d1\u008b\u00d0\u00b5 \u00d0\u00bf\u00d0\u00be\u00d0\u00ba\u00d0\u00b0\u00d0\u00b7\u00d0\u00b0\u00d1\u0082\u00d0\u00b5\u00d0\u00bb\u00d0\u00b8 \u00d1\u0087\u00d0\u00b8\u00d1\u0082\u00d0\u00b0\u00d1\u008e\u00d1\u0082\u00d1\u0081\u00d1\u008f \u00d0\u00be\u00d0\u00b4\u00d0\u00b8\u00d0\u00bd\u00d0\u00b0\u00d0\u00ba\u00d0\u00be\u00d0\u00b2\u00d0\u00be \u00d0\u0092\u00d0\u00b5\u00d1\u0081\u00d1\u008c \u00d0\u00b4\u00d0\u00b5\u00d0\u00bd\u00d1\u008c \u00d0\u00b2 Excel \u00e2\u0080\u0094 \u00d1\u008d\u00d1\u0082\u00d0\u00be \u00d0\u00bd\u00d0\u00b5 \u00d0\u00b0\u00d0\u00bd\u00d0\u00b0\u00d0\u00bb\u00d0\u00b8\u00d0\u00b7 \u00d0\u009f\u00d0\u00b5\u00d1\u0080\u00d0\u00b5\u00d0\u00bd\u00d0\u00be\u00d1\u0081 \u00d0\u00b4\u00d0\u00b0\u00d0\u00bd\u00d0\u00bd\u00d1\u008b\u00d1\u0085, \u00d1\u0080\u00d1\u0083\u00d1\u0087\u00d0\u00bd\u00d0\u00be\u00d0\u00b9 \u00d0\u00bf\u00d0\u00b5\u00d1\u0080\u00d0\u00b5\u00d1\u0081\u00d1\u0087\u00d1\u0091\u00d1\u0082, \u00d0\u00b2\u00d1\u0091\u00d1\u0080\u00d1\u0081\u00d1\u0082\u00d0\u00ba\u00d0\u00b0 \u00d0\u00be\u00d1\u0082\u00d1\u0087\u00d1\u0091\u00d1\u0082\u00d0\u00b0. \u00d0\u00a3\u00d1\u0085\u00d0\u00be\u00d0\u00b4\u00d0\u00b8\u00d1\u0082 \u00d0\u00b2\u00d0\u00b5\u00d1\u0081\u00d1\u008c \u00d1\u0080\u00d0\u00b0\u00d0\u00b1\u00d0\u00be\u00d1\u0087\u00d0\u00b8\u00d0\u00b9 \u00d0\u00b4\u00d0\u00b5\u00d0\u00bd\u00d1\u008c, \u00d0\u00b8 \u00d0\u00b2\u00d1\u0081\u00d1\u0091 \u00d1\u0080\u00d0\u00b0\u00d0\u00b2\u00d0\u00bd\u00d0\u00be \u00d0\u00b3\u00d0\u00b4\u00d0\u00b5-\u00d1\u0082\u00d0\u00be \u00d0\u00be\u00d1\u0088\u00d0\u00b8\u00d0\u00b1\u00d0\u00ba\u00d0\u00b0. \u00d0\u009e\u00d1\u0082\u00d1\u0087\u00d1\u0091\u00d1\u0082 \u00d0\u00b2 PDF \u00d0\u00b8\u00d0\u00bb\u00d0\u00b8 Excel \u00d0\u00b2 \u00d0\u00be\u00d0\u00b4\u00d0\u00b8\u00d0\u00bd \u00d0\u00ba\u00d0\u00bb\u00d0\u00b8\u00d0\u00ba \u00d0\u009e\u00d1\u0082\u00d0\u00ba\u00d1\u0080\u00d1\u008b\u00d0\u00bb \u00e2\u0080\u0094 \u00d0\u00bf\u00d0\u00be\u00d1\u0081\u00d0\u00bc\u00d0\u00be\u00d1\u0082\u00d1\u0080\u00d0\u00b5\u00d0\u00bb \u00e2\u0080\u0094 \u00d0\u00bf\u00d0\u00be\u00d1\u0082\u00d0\u00b5\u00d1\u0080\u00d1\u008f\u00d0\u00bb \u00d0\u009f\u00d0\u00be\u00d1\u0081\u00d0\u00bb\u00d0\u00b5 \u00d0\u00bf\u00d0\u00b5\u00d1\u0080\u00d0\u00b2\u00d0\u00be\u00d0\u00b3\u00d0\u00be \u00d0\u00bf\u00d1\u0080\u00d0\u00be\u00d1\u0081\u00d0\u00bc\u00d0\u00be\u00d1\u0082\u00d1\u0080\u00d0\u00b0 \u00d1\u0084\u00d0\u00b0\u00d0\u00b9\u00d0\u00bb \u00d0\u00b7\u00d0\u00b0\u00d0\u00ba\u00d1\u0080\u00d1\u008b\u00d1\u0082 \u00d0\u00b8 \u00d1\u0080\u00d0\u00b5\u00d0\u00b7\u00d1\u0083\u00d0\u00bb\u00d1\u008c\u00d1\u0082\u00d0\u00b0\u00d1\u0082 \u00d0\u00bf\u00d0\u00be\u00d1\u0082\u00d0\u00b5\u00d1\u0080\u00d1\u008f\u00d0\u00bd. \u00d0\u00a7\u00d0\u00b5\u00d1\u0080\u00d0\u00b5\u00d0\u00b7 \u00d0\u00bd\u00d0\u00b5\u00d0\u00b4\u00d0\u00b5\u00d0\u00bb\u00d1\u008e \u00d0\u00bf\u00d1\u0080\u00d0\u00b8\u00d1\u0085\u00d0\u00be\u00d0\u00b4\u00d0\u00b8\u00d1\u0082\u00d1\u0081\u00d1\u008f \u00d0\u00bd\u00d0\u00b0\u00d1\u0087\u00d0\u00b8\u00d0\u00bd\u00d0\u00b0\u00d1\u0082\u00d1\u008c \u00d0\u00b7\u00d0\u00b0\u00d0\u00bd\u00d0\u00be\u00d0\u00b2\u00d0\u00be. \u00d0\u009a\u00d0\u00b0\u00d0\u00b6\u00d0\u00b4\u00d1\u008b\u00d0\u00b9 \u00d0\u00be\u00d0\u00bf\u00d1\u008b\u00d1\u0082 \u00d1\u0085\u00d1\u0080\u00d0\u00b0\u00d0\u00bd\u00d0\u00b8\u00d1\u0082\u00d1\u0081\u00d1\u008f \u00d0\u00b8 \u00d0\u00be\u00d1\u0082\u00d0\u00ba\u00d1\u0080\u00d1\u008b\u00d0\u00b2\u00d0\u00b0\u00d0\u00b5\u00d1\u0082\u00d1\u0081\u00d1\u008f \u00d0\u00bf\u00d0\u00be\u00d0\u00b2\u00d1\u0082\u00d0\u00be\u00d1\u0080\u00d0\u00bd\u00d0\u00be \u00d0\u009e\u00d1\u0082 \u00d0\u00b8\u00d0\u00bc\u00d0\u00bf\u00d0\u00be\u00d1\u0080\u00d1\u0082\u00d0\u00b0 \u00d0\u00b4\u00d0\u00be \u00d0\u00b3\u00d0\u00be\u00d1\u0082\u00d0\u00be\u00d0\u00b2\u00d0\u00be\u00d0\u00b3\u00d0\u00be \u00d0\u00be\u00d1\u0082\u00d1\u0087\u00d1\u0091\u00d1\u0082\u00d0\u00b0 \u00d0\u0095\u00d0\u00b4\u00d0\u00b8\u00d0\u00bd\u00d0\u00b0\u00d1\u008f \u00d1\u0081\u00d1\u0080\u00d0\u00b5\u00d0\u00b4\u00d0\u00b0 \u00d0\u00b4\u00d0\u00bb\u00d1\u008f \u00d0\u00b2\u00d1\u0081\u00d0\u00b5\u00d1\u0085 \u00d1\u0080\u00d0\u00b5\u00d0\u00be\u00d0\u00bb\u00d0\u00be\u00d0\u00b3\u00d0\u00b8\u00d1\u0087\u00d0\u00b5\u00d1\u0081\u00d0\u00ba\u00d0\u00b8\u00d1\u0085 \u00d0\u00b8\u00d1\u0081\u00d0\u00bf\u00d1\u008b\u00d1\u0082\u00d0\u00b0\u00d0\u00bd\u00d0\u00b8\u00d0\u00b9 01 \u00d0\u0090\u00d0\u00b2\u00d1\u0082\u00d0\u00be\u00d0\u00bc\u00d0\u00b0\u00d1\u0082\u00d0\u00b8\u00d1\u0087\u00d0\u00b5\u00d1\u0081\u00d0\u00ba\u00d0\u00b8\u00d0\u00b9 \u00d0\u00b8\u00d0\u00bc\u00d0\u00bf\u00d0\u00be\u00d1\u0080\u00d1\u0082 \u00d0\u0097\u00d0\u00b0\u00d0\u00b1\u00d1\u0083\u00d0\u00b4\u00d1\u008c\u00d1\u0082\u00d0\u00b5 \u00d0\u00bf\u00d1\u0080\u00d0\u00be \u00d1\u0080\u00d1\u0083\u00d1\u0087\u00d0\u00bd\u00d1\u0083\u00d1\u008e \u00d0\u00ba\u00d0\u00be\u00d0\u00bd\u00d0\u00b2\u00d0\u00b5\u00d1\u0080\u00d1\u0082\u00d0\u00b0\u00d1\u0086\u00d0\u00b8\u00d1\u008e \u00d0\u00b2 Excel. \u00d0\u009f\u00d1\u0080\u00d0\u00be\u00d0\u00b3\u00d1\u0080\u00d0\u00b0\u00d0\u00bc\u00d0\u00bc\u00d0\u00b0 \u00d1\u0080\u00d0\u00b0\u00d1\u0081\u00d0\u00bf\u00d0\u00be\u00d0\u00b7\u00d0\u00bd\u00d0\u00b0\u00d1\u0091\u00d1\u0082 \u00d1\u0081\u00d1\u0082\u00d1\u0080\u00d1\u0083\u00d0\u00ba\u00d1\u0082\u00d1\u0083\u00d1\u0080\u00d1\u0083 \u00d1\u0081\u00d1\u008b\u00d1\u0080\u00d0\u00be\u00d0\u00b3\u00d0\u00be \u00d1\u0084\u00d0\u00b0\u00d0\u00b9\u00d0\u00bb\u00d0\u00b0 \u00d0\u00b8 \u00d0\u00bc\u00d0\u00b3\u00d0\u00bd\u00d0\u00be\u00d0\u00b2\u00d0\u00b5\u00d0\u00bd\u00d0\u00bd\u00d0\u00be \u00d0\u00bf\u00d0\u00b5\u00d1\u0080\u00d0\u00b5\u00d0\u00bd\u00d0\u00be\u00d1\u0081\u00d0\u00b8\u00d1\u0082 \u00d0\u00b4\u00d0\u00b0\u00d0\u00bd\u00d0\u00bd\u00d1\u008b\u00d0\u00b5 \u00d0\u00bd\u00d0\u00b0 \u00d0\u00b5\u00d0\u00b4\u00d0\u00b8\u00d0\u00bd\u00d1\u008b\u00d0\u00b9 \u00d0\u00b3\u00d1\u0080\u00d0\u00b0\u00d1\u0084\u00d0\u00b8\u00d0\u00ba. Grace (M5600, M3600) Chandler (3500, 7500) Fann (35, 75, iGEL) OFITE, BSL-R1, Brookfield .xls .csv .dat \u00d0\u0095\u00d0\u00b4\u00d0\u00b8\u00d0\u00bd\u00d0\u00b0\u00d1\u008f \u00d0\u0091\u00d0\u00b0\u00d0\u00b7\u00d0\u00b0 \u00d0\u009e\u00d1\u0081\u00d1\u0082\u00d0\u00b2\u00d0\u00b0\u00d0\u00bb\u00d1\u008c\u00d0\u00b4\u00d0\u00b0-\u00d0\u00b4\u00d0\u00b5 \u00d0\u0092\u00d0\u00b0\u00d0\u00b0\u00d0\u00bb\u00d0\u00b5 \u00d0\u0091\u00d0\u00b8\u00d0\u00bd\u00d0\u00b3\u00d0\u00b0\u00d0\u00bc\u00d0\u00b0 \u00d0\u009f\u00d0\u00bb\u00d0\u00b0\u00d1\u0081\u00d1\u0082\u00d0\u00b8\u00d1\u0087. \u00d0\u00b2\u00d1\u008f\u00d0\u00b7\u00d0\u00ba\u00d0\u00be\u00d1\u0081\u00d1\u0082\u00d1\u008c (PV) 32.4 cP \u00d0\u0094\u00d0\u009d\u00d0\u00a1 (YP) 18.5 lb/100ft\u00c2\u00b2 \u00d0\u0098\u00d0\u00bd\u00d0\u00b4\u00d0\u00b5\u00d0\u00ba\u00d1\u0081 \u00d1\u0082\u00d0\u00b5\u00d1\u0087\u00d0\u00b5\u00d0\u00bd\u00d0\u00b8\u00d1\u008f (n) 0.724 \u00e2\u0080\u0094 \u00d0\u009f\u00d0\u00be\u00d0\u00ba\u00d0\u00b0\u00d0\u00b7. \u00d0\u00ba\u00d0\u00be\u00d0\u00bd\u00d1\u0081\u00d0\u00b8\u00d1\u0081\u00d1\u0082. (K) 1.492 eq cp n' (\u00d0\u00be\u00d0\u00b1\u00d0\u00be\u00d0\u00b1\u00d1\u0089.) 0.686 \u00e2\u0080\u0094 K' (\u00d0\u00be\u00d0\u00b1\u00d0\u00be\u00d0\u00b1\u00d1\u0089.) 1.821 eq cp 02 \u00d0\u009c\u00d0\u00b0\u00d1\u0082\u00d0\u00b5\u00d0\u00bc\u00d0\u00b0\u00d1\u0082\u00d0\u00b8\u00d0\u00ba\u00d0\u00b0 \u00d0\u00b1\u00d0\u00b5\u00d0\u00b7 \u00d0\u00be\u00d1\u0088\u00d0\u00b8\u00d0\u00b1\u00d0\u00be\u00d0\u00ba \u00d0\u00a1\u00d0\u00b8\u00d1\u0081\u00d1\u0082\u00d0\u00b5\u00d0\u00bc\u00d0\u00b0 \u00d1\u0081\u00d0\u00b0\u00d0\u00bc\u00d0\u00b0 \u00d0\u00bd\u00d0\u00b0\u00d1\u0085\u00d0\u00be\u00d0\u00b4\u00d0\u00b8\u00d1\u0082 \u00d1\u0080\u00d0\u00b0\u00d0\u00b1\u00d0\u00be\u00d1\u0087\u00d0\u00b8\u00d0\u00b5 \u00d1\u0086\u00d0\u00b8\u00d0\u00ba\u00d0\u00bb\u00d1\u008b \u00d0\u00be\u00d0\u00bf\u00d1\u008b\u00d1\u0082\u00d0\u00b0 (\u00d0\u00bd\u00d0\u00b0\u00d0\u00bf\u00d1\u0080\u00d0\u00b8\u00d0\u00bc\u00d0\u00b5\u00d1\u0080, API \u00d1\u0081\u00d1\u0082\u00d1\u0083\u00d0\u00bf\u00d0\u00b5\u00d0\u00bd\u00d0\u00b8) \u00d0\u00b8 \u00d0\u00be\u00d1\u0082\u00d1\u0081\u00d0\u00b5\u00d0\u00ba\u00d0\u00b0\u00d0\u00b5\u00d1\u0082 \u00d0\u00bf\u00d0\u00b0\u00d1\u0080\u00d0\u00b0\u00d0\u00b7\u00d0\u00b8\u00d1\u0082\u00d0\u00bd\u00d1\u008b\u00d0\u00b9 \u00d1\u0088\u00d1\u0083\u00d0\u00bc. \u00d0\u00a0\u00d0\u00b0\u00d1\u0081\u00d1\u0087\u00d0\u00b5\u00d1\u0082 \u00d1\u0080\u00d0\u00b5\u00d0\u00be\u00d0\u00bb\u00d0\u00be\u00d0\u00b3\u00d0\u00b8\u00d1\u0087\u00d0\u00b5\u00d1\u0081\u00d0\u00ba\u00d0\u00b8\u00d1\u0085 \u00d0\u00bc\u00d0\u00be\u00d0\u00b4\u00d0\u00b5\u00d0\u00bb\u00d0\u00b5\u00d0\u00b9 (\u00d1\u0081\u00d1\u0082\u00d0\u00b5\u00d0\u00bf\u00d0\u00b5\u00d0\u00bd\u00d0\u00bd\u00d0\u00be\u00d0\u00b9 \u00d0\u009e\u00d1\u0081\u00d1\u0082\u00d0\u00b2\u00d0\u00b0\u00d0\u00bb\u00d1\u008c\u00d0\u00b4\u00d0\u00b0-\u00d0\u00b4\u00d0\u00b5 \u00d0\u0092\u00d0\u00b0\u00d0\u00b0\u00d0\u00bb\u00d0\u00b5 \u00d0\u00b8 \u00d0\u0091\u00d0\u00b8\u00d0\u00bd\u00d0\u00b3\u00d0\u00b0\u00d0\u00bc\u00d0\u00b0) \u00d0\u00bf\u00d1\u0080\u00d0\u00be\u00d0\u00b8\u00d1\u0081\u00d1\u0085\u00d0\u00be\u00d0\u00b4\u00d0\u00b8\u00d1\u0082 \u00d0\u00b0\u00d0\u00b2\u00d1\u0082\u00d0\u00be\u00d0\u00bc\u00d0\u00b0\u00d1\u0082\u00d0\u00b8\u00d1\u0087\u00d0\u00b5\u00d1\u0081\u00d0\u00ba\u00d0\u00b8. \u00d0\u009f\u00d1\u0080\u00d0\u00be\u00d0\u00b3\u00d1\u0080\u00d0\u00b0\u00d0\u00bc\u00d0\u00bc\u00d0\u00b0 \u00d0\u00b2\u00d1\u008b\u00d0\u00b2\u00d0\u00b5\u00d0\u00b4\u00d0\u00b5\u00d1\u0082 \u00d1\u0082\u00d0\u00be\u00d1\u0087\u00d0\u00bd\u00d1\u008b\u00d0\u00b5 \u00d0\u00bc\u00d0\u00b5\u00d1\u0082\u00d1\u0080\u00d0\u00b8\u00d0\u00ba\u00d0\u00b8 n, K, YP, PV \u00d0\u00b2 \u00d0\u00b4\u00d0\u00be\u00d0\u00bb\u00d1\u008e \u00d1\u0081\u00d0\u00b5\u00d0\u00ba\u00d1\u0083\u00d0\u00bd\u00d0\u00b4\u00d1\u008b \u00e2\u0080\u0094 \u00d0\u00b2\u00d0\u00b0\u00d0\u00bc \u00d0\u00be\u00d1\u0081\u00d1\u0082\u00d0\u00b0\u00d1\u0091\u00d1\u0082\u00d1\u0081\u00d1\u008f \u00d1\u0082\u00d0\u00be\u00d0\u00bb\u00d1\u008c\u00d0\u00ba\u00d0\u00be \u00d0\u00bf\u00d0\u00be\u00d0\u00b4\u00d1\u0082\u00d0\u00b2\u00d0\u00b5\u00d1\u0080\u00d0\u00b4\u00d0\u00b8\u00d1\u0082\u00d1\u008c \u00d1\u0080\u00d0\u00b5\u00d0\u00b7\u00d1\u0083\u00d0\u00bb\u00d1\u008c\u00d1\u0082\u00d0\u00b0\u00d1\u0082. 03 \u00d0\u00a1\u00d1\u0080\u00d0\u00b0\u00d0\u00b2\u00d0\u00bd\u00d0\u00b5\u00d0\u00bd\u00d0\u00b8\u00d0\u00b5 \u00d0\u00b8 \u00d0\u00b1\u00d1\u0080\u00d0\u00b5\u00d0\u00bd\u00d0\u00b4\u00d0\u00b8\u00d1\u0080\u00d0\u00be\u00d0\u00b2\u00d0\u00b0\u00d0\u00bd\u00d0\u00bd\u00d1\u008b\u00d0\u00b5 \u00d0\u00be\u00d1\u0082\u00d1\u0087\u00d1\u0091\u00d1\u0082\u00d1\u008b \u00d0\u00a1\u00d1\u0080\u00d0\u00b0\u00d0\u00b2\u00d0\u00bd\u00d0\u00b8\u00d0\u00b2\u00d0\u00b0\u00d0\u00b9\u00d1\u0082\u00d0\u00b5 \u00d0\u00b4\u00d0\u00be 5 \u00d0\u00be\u00d0\u00bf\u00d1\u008b\u00d1\u0082\u00d0\u00be\u00d0\u00b2 \u00d0\u00bd\u00d0\u00b0 \u00d0\u00b5\u00d0\u00b4\u00d0\u00b8\u00d0\u00bd\u00d1\u008b\u00d1\u0085 \u00d0\u00be\u00d1\u0081\u00d1\u008f\u00d1\u0085, \u00d1\u0087\u00d1\u0082\u00d0\u00be\u00d0\u00b1\u00d1\u008b \u00d0\u00bd\u00d0\u00b0\u00d0\u00b3\u00d0\u00bb\u00d1\u008f\u00d0\u00b4\u00d0\u00bd\u00d0\u00be \u00d0\u00b2\u00d0\u00b8\u00d0\u00b4\u00d0\u00b5\u00d1\u0082\u00d1\u008c \u00d0\u00b4\u00d0\u00b5\u00d0\u00b3\u00d1\u0080\u00d0\u00b0\u00d0\u00b4\u00d0\u00b0\u00d1\u0086\u00d0\u00b8\u00d1\u008e \u00d0\u00b3\u00d0\u00b5\u00d0\u00bb\u00d1\u008f \u00d0\u00b8\u00d0\u00bb\u00d0\u00b8 \u00d1\u0080\u00d0\u00b0\u00d0\u00b7\u00d0\u00bd\u00d0\u00b8\u00d1\u0086\u00d1\u0083 \u00d0\u00bf\u00d0\u00b0\u00d1\u0080\u00d1\u0082\u00d0\u00b8\u00d0\u00b9. \u00d0\u009e\u00d0\u00b4\u00d0\u00b8\u00d0\u00bd \u00d0\u00ba\u00d0\u00bb\u00d0\u00b8\u00d0\u00ba \u00e2\u0080\u0094 \u00d0\u00b8 \u00d0\u00bf\u00d1\u0080\u00d0\u00be\u00d0\u00b3\u00d1\u0080\u00d0\u00b0\u00d0\u00bc\u00d0\u00bc\u00d0\u00b0 \u00d0\u00b3\u00d0\u00b5\u00d0\u00bd\u00d0\u00b5\u00d1\u0080\u00d0\u00b8\u00d1\u0080\u00d1\u0083\u00d0\u00b5\u00d1\u0082 \u00d1\u0081\u00d1\u0082\u00d1\u0080\u00d0\u00be\u00d0\u00b3\u00d0\u00b8\u00d0\u00b9 PDF-\u00d0\u00be\u00d1\u0082\u00d1\u0087\u00d1\u0091\u00d1\u0082 \u00d1\u0081 \u00d0\u00b2\u00d0\u00b0\u00d1\u0088\u00d0\u00b8\u00d0\u00bc \u00d0\u00bb\u00d0\u00be\u00d0\u00b3\u00d0\u00be\u00d1\u0082\u00d0\u00b8\u00d0\u00bf\u00d0\u00be\u00d0\u00bc, \u00d0\u00b3\u00d1\u0080\u00d0\u00b0\u00d1\u0084\u00d0\u00b8\u00d0\u00ba\u00d0\u00b0\u00d0\u00bc\u00d0\u00b8 \u00d0\u00b8 \u00d1\u0081\u00d0\u00b2\u00d0\u00be\u00d0\u00b4\u00d0\u00bd\u00d1\u008b\u00d0\u00bc\u00d0\u00b8 \u00d1\u0082\u00d0\u00b0\u00d0\u00b1\u00d0\u00bb\u00d0\u00b8\u00d1\u0086\u00d0\u00b0\u00d0\u00bc\u00d0\u00b8 \u00d0\u00b4\u00d0\u00bb\u00d1\u008f \u00d0\u00b7\u00d0\u00b0\u00d0\u00ba\u00d0\u00b0\u00d0\u00b7\u00d1\u0087\u00d0\u00b8\u00d0\u00ba\u00d0\u00b0. RheoLab \u00d0\u009e\u00d1\u0082\u00d1\u0087\u00d1\u0091\u00d1\u0082 \u00d0\u00be\u00d0\u00b1 \u00d0\u00b8\u00d1\u0081\u00d1\u0081\u00d0\u00bb\u00d0\u00b5\u00d0\u00b4\u00d0\u00be\u00d0\u00b2\u00d0\u00b0\u00d0\u00bd\u00d0\u00b8\u00d0\u00b8 \u00e2\u0084\u0096441 \u00d0\u009f\u00d1\u0080\u00d0\u00be\u00d0\u00b5\u00d0\u00ba\u00d1\u0082: \u00d0\u00a1\u00d0\u00ba\u00d0\u00b2\u00d0\u00b0\u00d0\u00b6\u00d0\u00b8\u00d0\u00bd\u00d0\u00b0 74-\u00d0\u00b1\u00d0\u00b8\u00d1\u0081, \u00d0\u0097\u00d0\u00b0\u00d0\u00ba\u00d0\u00b0\u00d0\u00b7\u00d1\u0087\u00d0\u00b8\u00d0\u00ba: \u00d0\u0093\u00d0\u00b0\u00d0\u00b7\u00d0\u009d\u00d0\u00b5\u00d1\u0084\u00d1\u0082\u00d1\u008c \u00d0\u009f\u00d0\u00b0\u00d1\u0080\u00d0\u00b0\u00d0\u00bc\u00d0\u00b5\u00d1\u0082\u00d1\u0080 \u00d0\u009f\u00d0\u00be\u00d0\u00ba\u00d0\u00b0\u00d0\u00b7\u00d0\u00b0\u00d1\u0082\u00d0\u00b5\u00d0\u00bb\u00d1\u008c PV (Plastic Viscosity) 35.0 cP YP (Yield Point) 14.2 lb/100ft\u00c2\u00b2 \u00d0\u0093\u00d0\u00b5\u00d0\u00bb\u00d1\u008c 10 \u00d1\u0081\u00d0\u00b5\u00d0\u00ba / 10 \u00d0\u00bc\u00d0\u00b8\u00d0\u00bd 6 / 12 lb/100ft\u00c2\u00b2 \u00d0\u00ad\u00d0\u00ba\u00d1\u0081\u00d0\u00bf\u00d0\u00be\u00d1\u0080\u00d1\u0082 \u00d0\u00b2 PDF \u00d0\u009f\u00d0\u00be\u00d1\u0081\u00d0\u00bc\u00d0\u00be\u00d1\u0082\u00d1\u0080\u00d0\u00b8\u00d1\u0082\u00d0\u00b5, \u00d0\u00ba\u00d0\u00b0\u00d0\u00ba \u00d1\u008d\u00d1\u0082\u00d0\u00be \u00d1\u0080\u00d0\u00b0\u00d0\u00b1\u00d0\u00be\u00d1\u0082\u00d0\u00b0\u00d0\u00b5\u00d1\u0082 \u00d0\u009a\u00d0\u00be\u00d1\u0080\u00d0\u00be\u00d1\u0082\u00d0\u00ba\u00d0\u00b8\u00d0\u00b5 \u00d1\u0080\u00d0\u00be\u00d0\u00bb\u00d0\u00b8\u00d0\u00ba\u00d0\u00b8 \u00d0\u00bf\u00d0\u00be \u00d0\u00be\u00d1\u0081\u00d0\u00bd\u00d0\u00be\u00d0\u00b2\u00d0\u00bd\u00d1\u008b\u00d0\u00bc \u00d1\u0081\u00d1\u0086\u00d0\u00b5\u00d0\u00bd\u00d0\u00b0\u00d1\u0080\u00d0\u00b8\u00d1\u008f\u00d0\u00bc \u00e2\u0080\u0094 \u00d0\u00b1\u00d0\u00b5\u00d0\u00b7 \u00d0\u00bb\u00d0\u00b8\u00d1\u0088\u00d0\u00bd\u00d0\u00b8\u00d1\u0085 \u00d1\u0081\u00d0\u00bb\u00d0\u00be\u00d0\u00b2, \u00d1\u0082\u00d0\u00be\u00d0\u00bb\u00d1\u008c\u00d0\u00ba\u00d0\u00be \u00d0\u00bd\u00d1\u0083\u00d0\u00b6\u00d0\u00bd\u00d1\u008b\u00d0\u00b5 \u00d1\u0088\u00d0\u00b0\u00d0\u00b3\u00d0\u00b8. \u00d0\u00a1\u00d0\u00ba\u00d0\u00be\u00d1\u0080\u00d0\u00be \u00d0\u009d\u00d0\u00b0\u00d1\u0081\u00d1\u0082\u00d1\u0080\u00d0\u00be\u00d0\u00b9\u00d0\u00ba\u00d0\u00b0 \u00d0\u00bf\u00d1\u0080\u00d0\u00be\u00d0\u00b3\u00d1\u0080\u00d0\u00b0\u00d0\u00bc\u00d0\u00bc\u00d1\u008b \u00d0\u009f\u00d0\u00b5\u00d1\u0080\u00d0\u00b2\u00d1\u008b\u00d0\u00b9 \u00d0\u00b7\u00d0\u00b0\u00d0\u00bf\u00d1\u0083\u00d1\u0081\u00d0\u00ba, \u00d0\u00be\u00d1\u0081\u00d0\u00bd\u00d0\u00be\u00d0\u00b2\u00d0\u00bd\u00d1\u008b\u00d0\u00b5 \u00d0\u00bf\u00d0\u00b0\u00d1\u0080\u00d0\u00b0\u00d0\u00bc\u00d0\u00b5\u00d1\u0082\u00d1\u0080\u00d1\u008b \u00d0\u00b8 \u00d0\u00ba\u00d0\u00be\u00d1\u0080\u00d0\u00be\u00d1\u0082\u00d0\u00ba\u00d0\u00b8\u00d0\u00b9 \u00d0\u00bc\u00d0\u00b0\u00d1\u0080\u00d1\u0088\u00d1\u0080\u00d1\u0083\u00d1\u0082 \u00d0\u00b4\u00d0\u00be \u00d0\u00bf\u00d0\u00b5\u00d1\u0080\u00d0\u00b2\u00d0\u00be\u00d0\u00b3\u00d0\u00be \u00d1\u0080\u00d0\u00b5\u00d0\u00b7\u00d1\u0083\u00d0\u00bb\u00d1\u008c\u00d1\u0082\u00d0\u00b0\u00d1\u0082\u00d0\u00b0. \u00d0\u00a1\u00d0\u00ba\u00d0\u00be\u00d1\u0080\u00d0\u00be \u00d0\u00a0\u00d0\u00b0\u00d0\u00b1\u00d0\u00be\u00d1\u0082\u00d0\u00b0 \u00d1\u0081 \u00d0\u00b1\u00d0\u00b0\u00d0\u00b7\u00d0\u00be\u00d0\u00b9 \u00d0\u00b4\u00d0\u00b0\u00d0\u00bd\u00d0\u00bd\u00d1\u008b\u00d1 \u00d0\u009a\u00d0\u00b0\u00d0\u00ba \u00d1\u0083\u00d1\u0081\u00d1\u0082\u00d1\u0080\u00d0\u00be\u00d0\u00b5\u00d0\u00bd\u00d0\u00b0 \u00d0\u00b1\u00d0\u00b8\u00d0\u00b1\u00d0\u00bb\u00d0\u00b8\u00d0\u00be\u00d1\u0082\u00d0\u00b5\u00d0\u00ba\u00d0\u00b0 \u00d0\u00be\u00d0\u00bf\u00d1\u008b\u00d1\u0082\u00d0\u00be\u00d0\u00b2, \u00d0\u00bf\u00d0\u00be\u00d0\u00b8\u00d1\u0081\u00d0\u00ba \u00d0\u00b8 \u00d0\u00bf\u00d0\u00be\u00d0\u00b2\u00d1\u0082\u00d0\u00be\u00d1\u0080\u00d0\u00bd\u00d0\u00be\u00d0\u00b5 \u00d0\u00be\u00d1\u0082\u00d0\u00ba\u00d1\u0080\u00d1\u008b\u00d1\u0082\u00d0\u00b8\u00d0\u00b5 \u00d1\u0080\u00d0\u00b5\u00d0\u00b7\u00d1\u0083\u00d0\u00bb\u00d1\u008c\u00d1\u0082\u00d0\u00b0\u00d1\u0082\u00d0\u00be\u00d0\u00b2. \u00d0\u00a1\u00d0\u00ba\u00d0\u00be\u00d1\u0080\u00d0\u00be \u00d0\u0092\u00d0\u00ba\u00d0\u00bb\u00d0\u00b0\u00d0\u00b4\u00d0\u00ba\u00d0\u00b0 \u00c2\u00ab\u00d0\u00a1\u00d1\u0080\u00d0\u00b0\u00d0\u00b2\u00d0\u00bd\u00d0\u00b5\u00d0\u00bd\u00d0\u00b8\u00d0\u00b5\u00c2\u00bb \u00d0\u00a1\u00d1\u0080\u00d0\u00b0\u00d0\u00b2\u00d0\u00bd\u00d0\u00b5\u00d0\u00bd\u00d0\u00b8\u00d0\u00b5 \u00d0\u00bd\u00d0\u00b5\u00d1\u0081\u00d0\u00ba\u00d0\u00be\u00d0\u00bb\u00d1\u008c\u00d0\u00ba\u00d0\u00b8\u00d1\u0085 \u00d0\u00be\u00d0\u00bf\u00d1\u008b\u00d1\u0082\u00d0\u00be\u00d0\u00b2 \u00d0\u00bd\u00d0\u00b0 \u00d0\u00b5\u00d0\u00b4\u00d0\u00b8\u00d0\u00bd\u00d1\u008b\u00d1\u0085 \u00d0\u00be\u00d1\u0081\u00d1\u008f\u00d1\u0085 \u00d0\u00b4\u00d0\u00bb\u00d1\u008f \u00d0\u00bd\u00d0\u00b0\u00d0\u00b3\u00d0\u00bb\u00d1\u008f\u00d0\u00b4\u00d0\u00bd\u00d0\u00be\u00d0\u00b3\u00d0\u00be \u00d0\u00b0\u00d0\u00bd\u00d0\u00b0\u00d0\u00bb\u00d0\u00b8\u00d0\u00b7\u00d0\u00b0 \u00d1\u0080\u00d0\u00b5\u00d1\u0086\u00d0\u00b5\u00d0\u00bf\u00d1\u0082\u00d1\u0083\u00d1\u0080. \u00d0\u00a1\u00d0\u00ba\u00d0\u00be\u00d1\u0080\u00d0\u00be \u00d0\u0092\u00d1\u008b\u00d0\u00b3\u00d1\u0080\u00d1\u0083\u00d0\u00b7\u00d0\u00ba\u00d0\u00b0 \u00d0\u00be\u00d1\u0082\u00d1\u0087\u00d0\u00b5\u00d1\u0082\u00d0\u00be\u00d0\u00b2 \u00d0\u009a\u00d0\u00b0\u00d0\u00ba \u00d0\u00bf\u00d0\u00be\u00d0\u00bb\u00d1\u0083\u00d1\u0087\u00d0\u00b8\u00d1\u0082\u00d1\u008c PDF \u00d0\u00b8\u00d0\u00bb\u00d0\u00b8 Excel \u00d1\u0081 \u00d0\u00b3\u00d1\u0080\u00d0\u00b0\u00d1\u0084\u00d0\u00b8\u00d0\u00ba\u00d0\u00be\u00d0\u00bc \u00d0\u00b8 \u00d0\u00ba\u00d0\u00bb\u00d1\u008e\u00d1\u0087\u00d0\u00b5\u00d0\u00b2\u00d1\u008b\u00d0\u00bc\u00d0\u00b8 \u00d0\u00b7\u00d0\u00bd\u00d0\u00b0\u00d1\u0087\u00d0\u00b5\u00d0\u00bd\u00d0\u00b8\u00d1\u008f\u00d0\u00bc\u00d0\u00b8 \u00d0\u00b2 \u00d0\u00be\u00d0\u00b4\u00d0\u00b8\u00d0\u00bd \u00d0\u00ba\u00d0\u00bb\u00d0\u00b8\u00d0\u00ba. \u00d0\u009a\u00d0\u00be\u00d0\u00bc\u00d1\u0083 \u00d1\u008d\u00d1\u0082\u00d0\u00be \u00d0\u00b4\u00d0\u00b5\u00d0\u00b9\u00d1\u0081\u00d1\u0082\u00d0\u00b2\u00d0\u00b8\u00d1\u0082\u00d0\u00b5\u00d0\u00bb\u00d1\u008c\u00d0\u00bd\u00d0\u00be \u00d0\u00bd\u00d1\u0083\u00d0\u00b6\u00d0\u00bd\u00d0\u00be \u00d0\u009d\u00d0\u00b5\u00d1\u0084\u00d1\u0082\u00d0\u00b5\u00d1\u0081\u00d0\u00b5\u00d1\u0080\u00d0\u00b2\u00d0\u00b8\u00d1\u0081\u00d0\u00bd\u00d1\u008b\u00d0\u00b5 \u00d0\u00ba\u00d0\u00be\u00d0\u00bc\u00d0\u00bf\u00d0\u00b0\u00d0\u00bd\u00d0\u00b8\u00d0\u00b8 \u00d0\u0091\u00d1\u008b\u00d1\u0081\u00d1\u0082\u00d1\u0080\u00d0\u00b0\u00d1\u008f \u00d0\u00be\u00d0\u00b1\u00d1\u0080\u00d0\u00b0\u00d0\u00b1\u00d0\u00be\u00d1\u0082\u00d0\u00ba\u00d0\u00b0 \u00d0\u00b4\u00d0\u00b0\u00d0\u00bd\u00d0\u00bd\u00d1\u008b\u00d1\u0085 \u00d1\u0081 \u00d0\u00b1\u00d1\u0083\u00d1\u0080\u00d0\u00be\u00d0\u00b2\u00d1\u008b\u00d1\u0085, \u00d1\u0081\u00d1\u0080\u00d0\u00b0\u00d0\u00b2\u00d0\u00bd\u00d0\u00b5\u00d0\u00bd\u00d0\u00b8\u00d0\u00b5 \u00d0\u00be\u00d0\u00bf\u00d1\u008b\u00d1\u0082\u00d0\u00be\u00d0\u00b2 \u00d0\u00bf\u00d0\u00be \u00d1\u0081\u00d0\u00ba\u00d0\u00b2\u00d0\u00b0\u00d0\u00b6\u00d0\u00b8\u00d0\u00bd\u00d0\u00b0\u00d0\u00bc \u00d0\u00b8 \u00d1\u0081\u00d1\u0082\u00d0\u00b0\u00d0\u00bd\u00d0\u00b4\u00d0\u00b0\u00d1\u0080\u00d1\u0082\u00d0\u00bd\u00d1\u008b\u00d0\u00b9 \u00d0\u00be\u00d1\u0082\u00d1\u0087\u00d1\u0091\u00d1\u0082 \u00d0\u00b7\u00d0\u00b0\u00d0\u00ba\u00d0\u00b0\u00d0\u00b7\u00d1\u0087\u00d0\u00b8\u00d0\u00ba\u00d1\u0083 \u00d0\u00b1\u00d0\u00b5\u00d0\u00b7 \u00d1\u0080\u00d1\u0083\u00d1\u0087\u00d0\u00bd\u00d0\u00be\u00d0\u00b9 \u00d1\u0081\u00d0\u00b1\u00d0\u00be\u00d1\u0080\u00d0\u00ba\u00d0\u00b8. \u00d0\u009d\u00d0\u0098\u00d0\u0098 \u00d0\u00b8 \u00d0\u00bd\u00d0\u00b0\u00d1\u0083\u00d1\u0087\u00d0\u00bd\u00d1\u008b\u00d0\u00b5 \u00d1\u0086\u00d0\u00b5\u00d0\u00bd\u00d1\u0082\u00d1\u0080\u00d1\u008b \u00d0\u0090\u00d1\u0080\u00d1\u0085\u00d0\u00b8\u00d0\u00b2 \u00d0\u00be\u00d0\u00bf\u00d1\u008b\u00d1\u0082\u00d0\u00be\u00d0\u00b2 \u00d1\u0081 \u00d0\u00b2\u00d0\u00be\u00d1\u0081\u00d0\u00bf\u00d1\u0080\u00d0\u00be\u00d0\u00b8\u00d0\u00b7\u00d0\u00b2\u00d0\u00be\u00d0\u00b4\u00d0\u00b8\u00d0\u00bc\u00d0\u00be\u00d1\u0081\u00d1\u0082\u00d1\u008c\u00d1\u008e, \u00d1\u0081\u00d1\u0080\u00d0\u00b0\u00d0\u00b2\u00d0\u00bd\u00d0\u00b5\u00d0\u00bd\u00d0\u00b8\u00d0\u00b5 \u00d1\u0081\u00d0\u00b5\u00d1\u0080\u00d0\u00b8\u00d0\u00b9 \u00d0\u00bf\u00d0\u00be \u00d1\u0080\u00d0\u00b5\u00d1\u0086\u00d0\u00b5\u00d0\u00bf\u00d1\u0082\u00d1\u0083\u00d1\u0080\u00d0\u00b0\u00d0\u00bc \u00d0\u00b8 \u00d0\u00b3\u00d0\u00be\u00d1\u0082\u00d0\u00be\u00d0\u00b2\u00d1\u008b\u00d0\u00b5 \u00d0\u00b4\u00d0\u00b0\u00d0\u00bd\u00d0\u00bd\u00d1\u008b\u00d0\u00b5 \u00d0\u00b4\u00d0\u00bb\u00d1\u008f \u00d0\u00bf\u00d1\u0083\u00d0\u00b1\u00d0\u00bb\u00d0\u00b8\u00d0\u00ba\u00d0\u00b0\u00d1\u0086\u00d0\u00b8\u00d0\u00b9 \u00d0\u00b1\u00d0\u00b5\u00d0\u00b7 \u00d0\u00bf\u00d0\u00b5\u00d1\u0080\u00d0\u00b5\u00d1\u0081\u00d0\u00b1\u00d0\u00be\u00d1\u0080\u00d0\u00ba\u00d0\u00b8 \u00d1\u0082\u00d0\u00b0\u00d0\u00b1\u00d0\u00bb\u00d0\u00b8\u00d1\u0086. \u00d0\u009d\u00d0\u00b5\u00d1\u0084\u00d1\u0082\u00d0\u00b5\u00d0\u00b4\u00d0\u00be\u00d0\u00b1\u00d1\u008b\u00d0\u00b2\u00d0\u00b0\u00d1\u008e\u00d1\u0089\u00d0\u00b8\u00d0\u00b5 \u00d0\u00ba\u00d0\u00be\u00d0\u00bc\u00d0\u00bf\u00d0\u00b0\u00d0\u00bd\u00d0\u00b8\u00d0\u00b8 \u00d0\u009a\u00d0\u00be\u00d0\u00bd\u00d1\u0082\u00d1\u0080\u00d0\u00be\u00d0\u00bb\u00d1\u008c \u00d0\u00ba\u00d0\u00b0\u00d1\u0087\u00d0\u00b5\u00d1\u0081\u00d1\u0082\u00d0\u00b2\u00d0\u00b0 \u00d1\u0080\u00d0\u00b0\u00d1\u0081\u00d1\u0082\u00d0\u00b2\u00d0\u00be\u00d1\u0080\u00d0\u00be\u00d0\u00b2 \u00d0\u00b2 \u00d0\u00b5\u00d0\u00b4\u00d0\u00b8\u00d0\u00bd\u00d0\u00be\u00d0\u00bc \u00d1\u0084\u00d0\u00be\u00d1\u0080\u00d0\u00bc\u00d0\u00b0\u00d1\u0082\u00d0\u00b5, \u00d0\u00b8\u00d1\u0081\u00d1\u0082\u00d0\u00be\u00d1\u0080\u00d0\u00b8\u00d1\u008f \u00d0\u00bf\u00d0\u00be \u00d0\u00be\u00d0\u00b1\u00d1\u008a\u00d0\u00b5\u00d0\u00ba\u00d1\u0082\u00d0\u00b0\u00d0\u00bc \u00d0\u00b8 \u00d0\u00bf\u00d0\u00be\u00d0\u00bd\u00d1\u008f\u00d1\u0082\u00d0\u00bd\u00d0\u00b0\u00d1\u008f \u00d0\u00b1\u00d0\u00b0\u00d0\u00b7\u00d0\u00b0 \u00d0\u00b4\u00d0\u00bb\u00d1\u008f \u00d1\u0080\u00d0\u00b0\u00d0\u00b1\u00d0\u00be\u00d1\u0082\u00d1\u008b \u00d1\u0081\u00d1\u0083\u00d0\u00bf\u00d0\u00b5\u00d1\u0080\u00d0\u00b2\u00d0\u00b0\u00d0\u00b9\u00d0\u00b7\u00d0\u00b8\u00d0\u00bd\u00d0\u00b3\u00d0\u00b0. \u00d0\u009f\u00d1\u0080\u00d0\u00be\u00d0\u00b8\u00d0\u00b7\u00d0\u00b2\u00d0\u00be\u00d0\u00b4\u00d0\u00b8\u00d1\u0082\u00d0\u00b5\u00d0\u00bb\u00d0\u00b8 \u00d1\u0080\u00d0\u00b5\u00d0\u00b0\u00d0\u00b3\u00d0\u00b5\u00d0\u00bd\u00d1\u0082\u00d0\u00be\u00d0\u00b2 \u00d0\u00a1\u00d1\u0080\u00d0\u00b0\u00d0\u00b2\u00d0\u00bd\u00d0\u00b5\u00d0\u00bd\u00d0\u00b8\u00d0\u00b5 \u00d1\u0080\u00d0\u00b5\u00d1\u0086\u00d0\u00b5\u00d0\u00bf\u00d1\u0082\u00d1\u0083\u00d1\u0080 \u00d0\u00bd\u00d0\u00b0 \u00d0\u00be\u00d0\u00b1\u00d1\u0089\u00d0\u00b8\u00d1\u0085 \u00d0\u00be\u00d1\u0081\u00d1\u008f\u00d1\u0085, \u00d0\u00ba\u00d0\u00be\u00d0\u00bd\u00d1\u0082\u00d1\u0080\u00d0\u00be\u00d0\u00bb\u00d1\u008c \u00d1\u0081\u00d1\u0082\u00d0\u00b0\u00d0\u00b1\u00d0\u00b8\u00d0\u00bb\u00d1\u008c\u00d0\u00bd\u00d0\u00be\u00d1\u0081\u00d1\u0082\u00d0\u00b8 \u00d0\u00ba\u00d0\u00b0\u00d1\u0087\u00d0\u00b5\u00d1\u0081\u00d1\u0082\u00d0\u00b2\u00d0\u00b0 \u00d0\u00b8 \u00d1\u0083\u00d1\u0081\u00d0\u00ba\u00d0\u00be\u00d1\u0080\u00d0\u00b5\u00d0\u00bd\u00d0\u00b8\u00d0\u00b5 R&D \u00d0\u00b1\u00d0\u00b5\u00d0\u00b7 \u00d1\u0080\u00d1\u0083\u00d1\u0087\u00d0\u00bd\u00d0\u00be\u00d0\u00b3\u00d0\u00be \u00d1\u0081\u00d0\u00b2\u00d0\u00b5\u00d0\u00b4\u00d0\u00b5\u00d0\u00bd\u00d0\u00b8\u00d1\u008f \u00d0\u00b4\u00d0\u00b0\u00d0\u00bd\u00d0\u00bd\u00d1\u008b\u00d1\u0085. \u00d0\u00a1\u00d0\u00b2\u00d1\u008f\u00d0\u00b7\u00d0\u00b0\u00d1\u0082\u00d1\u008c\u00d1\u0081\u00d1\u008f \u00d1\u0081 \u00d0\u00ba\u00d0\u00be\u00d0\u00bc\u00d0\u00b0\u00d0\u00bd\u00d0\u00b4\u00d0\u00be\u00d0\u00b9 \u00d0\u0095\u00d1\u0081\u00d0\u00bb\u00d0\u00b8 \u00d1\u0085\u00d0\u00be\u00d1\u0082\u00d0\u00b8\u00d1\u0082\u00d0\u00b5 \u00d0\u00b1\u00d1\u008b\u00d1\u0081\u00d1\u0082\u00d1\u0080\u00d0\u00be \u00d0\u00bf\u00d0\u00be\u00d0\u00bd\u00d1\u008f\u00d1\u0082\u00d1\u008c, \u00d0\u00ba\u00d0\u00b0\u00d0\u00ba RheoLab \u00d0\u00bb\u00d1\u008f\u00d0\u00b6\u00d0\u00b5\u00d1\u0082 \u00d0\u00bd\u00d0\u00b0 \u00d0\u00b2\u00d0\u00b0\u00d1\u0088 \u00d0\u00bf\u00d1\u0080\u00d0\u00be\u00d1\u0086\u00d0\u00b5\u00d1\u0081\u00d1\u0081,\n        \u00d0\u00bd\u00d0\u00b0\u00d0\u00bf\u00d0\u00b8\u00d1\u0088\u00d0\u00b8\u00d1\u0082\u00d0\u00b5 \u00d0\u00bd\u00d0\u00b0\u00d0\u00bc. \u00d0\u0094\u00d0\u00be\u00d1\u0081\u00d1\u0082\u00d0\u00b0\u00d1\u0082\u00d0\u00be\u00d1\u0087\u00d0\u00bd\u00d0\u00be \u00d1\u0083\u00d0\u00ba\u00d0\u00b0\u00d0\u00b7\u00d0\u00b0\u00d1\u0082\u00d1\u008c \u00d0\u00bf\u00d1\u0080\u00d0\u00b8\u00d0\u00b1\u00d0\u00be\u00d1\u0080\u00d1\u008b, \u00d1\u0082\u00d0\u00b8\u00d0\u00bf\u00d1\u008b \u00d1\u0084\u00d0\u00b0\u00d0\u00b9\u00d0\u00bb\u00d0\u00be\u00d0\u00b2 \u00d0\u00b8 \u00d1\u0087\u00d1\u0082\u00d0\u00be \u00d1\u0081\u00d0\u00b5\u00d0\u00b9\u00d1\u0087\u00d0\u00b0\u00d1\u0081\n        \u00d0\u00bc\u00d0\u00b5\u00d1\u0088\u00d0\u00b0\u00d0\u00b5\u00d1\u0082 \u00d0\u00b2 \u00d1\u0080\u00d0\u00b0\u00d0\u00b1\u00d0\u00be\u00d1\u0082\u00d0\u00b5 \u00d1\u0081\u00d0\u00b8\u00d0\u00bb\u00d1\u008c\u00d0\u00bd\u00d0\u00b5\u00d0\u00b5 \u00d0\u00b2\u00d1\u0081\u00d0\u00b5\u00d0\u00b3\u00d0\u00be. \u00d0\u009e\u00d0\u00b1\u00d1\u0081\u00d1\u0083\u00d0\u00b4\u00d0\u00b8\u00d1\u0082\u00d1\u008c \u00d0\u00b2\u00d0\u00bd\u00d0\u00b5\u00d0\u00b4\u00d1\u0080\u00d0\u00b5\u00d0\u00bd\u00d0\u00b8\u00d0\u00b5 info@rheolab.site \u00d0\u009f\u00d0\u00be\u00d0\u00ba\u00d0\u00b0\u00d0\u00b7 \u00d0\u00bf\u00d1\u0080\u00d0\u00be\u00d0\u00b4\u00d1\u0083\u00d0\u00ba\u00d1\u0082\u00d0\u00b0, \u00d0\u00be\u00d0\u00b1\u00d1\u0081\u00d1\u0083\u00d0\u00b6\u00d0\u00b4\u00d0\u00b5\u00d0\u00bd\u00d0\u00b8\u00d0\u00b5 \u00d0\u00bb\u00d0\u00b8\u00d1\u0086\u00d0\u00b5\u00d0\u00bd\u00d0\u00b7\u00d0\u00b8\u00d0\u00b8 \u00d0\u00b8 \u00d1\u0080\u00d0\u00b0\u00d0\u00b7\u00d0\u00b1\u00d0\u00be\u00d1\u0080 \u00d0\u00b2\u00d0\u00b0\u00d1\u0088\u00d0\u00b8\u00d1\u0085 \u00d1\u0080\u00d0\u00b0\u00d0\u00b1\u00d0\u00be\u00d1\u0087\u00d0\u00b8\u00d1\u0085 \u00d1\u0081\u00d1\u0086\u00d0\u00b5\u00d0\u00bd\u00d0\u00b0\u00d1\u0080\u00d0\u00b8\u00d0\u00b5\u00d0\u00b2. \u00d0\u00a2\u00d0\u00b5\u00d1\u0085\u00d0\u00bd\u00d0\u00b8\u00d1\u0087\u00d0\u00b5\u00d1\u0081\u00d0\u00ba\u00d0\u00b0\u00d1\u008f \u00d0\u00bf\u00d0\u00be\u00d0\u00b4\u00d0\u00b4\u00d0\u00b5\u00d1\u0080\u00d0\u00b6\u00d0\u00ba\u00d0\u00b0 support@rheolab.site \u00d0\u0097\u00d0\u00b0\u00d0\u00bf\u00d1\u0083\u00d1\u0081\u00d0\u00ba, \u00d0\u00b8\u00d0\u00bc\u00d0\u00bf\u00d0\u00be\u00d1\u0080\u00d1\u0082 \u00d1\u0084\u00d0\u00b0\u00d0\u00b9\u00d0\u00bb\u00d0\u00be\u00d0\u00b2, \u00d0\u00bf\u00d0\u00b5\u00d1\u0080\u00d0\u00b5\u00d0\u00bd\u00d0\u00be\u00d1\u0081 \u00d0\u00b4\u00d0\u00b0\u00d0\u00bd\u00d0\u00bd\u00d1\u008b\u00d1\u0085 \u00d0\u00b8 \u00d0\u00b2\u00d0\u00be\u00d0\u00bf\u00d1\u0080\u00d0\u00be\u00d1\u0081\u00d1\u008b \u00d0\u00bf\u00d0\u00be \u00d1\u0080\u00d0\u00b0\u00d0\u00b1\u00d0\u00be\u00d1\u0082\u00d0\u00b5 \u00d0\u00bf\u00d1\u0080\u00d0\u00be\u00d0\u00b3\u00d1\u0080\u00d0\u00b0\u00d0\u00bc\u00d0\u00bc\u00d1\u008b. \u00d0\u00a7\u00d1\u0082\u00d0\u00be \u00d0\u00bf\u00d1\u0080\u00d0\u00b8\u00d1\u0081\u00d0\u00bb\u00d0\u00b0\u00d1\u0082\u00d1\u008c \u00d0\u00b4\u00d0\u00bb\u00d1\u008f \u00d0\u00b1\u00d1\u008b\u00d1\u0081\u00d1\u0082\u00d1\u0080\u00d0\u00be\u00d0\u00b3\u00d0\u00be \u00d0\u00be\u00d1\u0082\u00d0\u00b2\u00d0\u00b5\u00d1\u0082\u00d0\u00b0 \u00d0\u00ba\u00d0\u00b0\u00d0\u00ba\u00d0\u00b8\u00d0\u00b5 \u00d0\u00bf\u00d1\u0080\u00d0\u00b8\u00d0\u00b1\u00d0\u00be\u00d1\u0080\u00d1\u008b \u00d0\u00b8 \u00d1\u0084\u00d0\u00be\u00d1\u0080\u00d0\u00bc\u00d0\u00b0\u00d1\u0082\u00d1\u008b \u00d1\u0084\u00d0\u00b0\u00d0\u00b9\u00d0\u00bb\u00d0\u00be\u00d0\u00b2 \u00d1\u0083 \u00d0\u00b2\u00d0\u00b0\u00d1\u0081 \u00d0\u00b2 \u00d1\u0080\u00d0\u00b0\u00d0\u00b1\u00d0\u00be\u00d1\u0082\u00d0\u00b5; \u00d1\u0087\u00d1\u0082\u00d0\u00be \u00d1\u0081\u00d0\u00b5\u00d0\u00b9\u00d1\u0087\u00d0\u00b0\u00d1\u0081 \u00d0\u00bd\u00d0\u00b5\u00d1\u0083\u00d0\u00b4\u00d0\u00be\u00d0\u00b1\u00d0\u00bd\u00d0\u00be: \u00d1\u0085\u00d1\u0080\u00d0\u00b0\u00d0\u00bd\u00d0\u00b5\u00d0\u00bd\u00d0\u00b8\u00d0\u00b5, \u00d1\u0081\u00d1\u0080\u00d0\u00b0\u00d0\u00b2\u00d0\u00bd\u00d0\u00b5\u00d0\u00bd\u00d0\u00b8\u00d0\u00b5, \u00d0\u00be\u00d1\u0082\u00d1\u0087\u00d0\u00b5\u00d1\u0082\u00d1\u008b \u00d0\u00b8\u00d0\u00bb\u00d0\u00b8 \u00d0\u00bf\u00d0\u00be\u00d0\u00b8\u00d1\u0081\u00d0\u00ba; \u00d0\u00bd\u00d1\u0083\u00d0\u00b6\u00d0\u00b5\u00d0\u00bd \u00d0\u00bb\u00d0\u00b8 \u00d0\u00bf\u00d0\u00be\u00d0\u00ba\u00d0\u00b0\u00d0\u00b7, \u00d0\u00bf\u00d1\u0080\u00d0\u00be\u00d0\u00b1\u00d0\u00bd\u00d1\u008b\u00d0\u00b9 \u00d0\u00b7\u00d0\u00b0\u00d0\u00bf\u00d1\u0083\u00d1\u0081\u00d0\u00ba \u00d0\u00b8\u00d0\u00bb\u00d0\u00b8 \u00d1\u0080\u00d0\u00b0\u00d0\u00b7\u00d0\u00b1\u00d0\u00be\u00d1\u0080 \u00d0\u00b2\u00d0\u00b0\u00d1\u0088\u00d0\u00b8\u00d1\u0085 \u00d0\u00b4\u00d0\u00b0\u00d0\u00bd\u00d0\u00bd\u00d1\u008b\u00d1\u0085. \u00d0\u009d\u00d0\u00b0\u00d0\u00bf\u00d0\u00b8\u00d1\u0081\u00d0\u00b0\u00d1\u0082\u00d1\u008c \u00d0\u00bd\u00d0\u00b0\u00d0\u00bc",
    "internal_links": [
      {
        "url": "https://rheolab.site/#main-content",
        "text": "\u00d0\u009f\u00d0\u00b5\u00d1\u0080\u00d0\u00b5\u00d0\u00b9\u00d1\u0082\u00d0\u00b8 \u00d0\u00ba \u00d1\u0081\u00d0\u00be\u00d0\u00b4\u00d0\u00b5\u00d1\u0080\u00d0\u00b6\u00d0\u00b8\u00d0\u00bc\u00d0\u00be\u00d0\u00bc\u00d1\u0083"
      },
      {
        "url": "https://rheolab.site/download/latest",
        "text": "\u00d0\u00a1\u00d0\u00ba\u00d0\u00b0\u00d1\u0087\u00d0\u00b0\u00d1\u0082\u00d1\u008c \u00d0\u00b1\u00d0\u00b5\u00d1\u0081\u00d0\u00bf\u00d0\u00bb\u00d0\u00b0\u00d1\u0082\u00d0\u00bd\u00d0\u00be \u00d0\u00b4\u00d0\u00bb\u00d1\u008f Windows"
      },
      {
        "url": "https://rheolab.site/#contact",
        "text": "\u00d0\u009d\u00d0\u00b0\u00d0\u00bf\u00d0\u00b8\u00d1\u0081\u00d0\u00b0\u00d1\u0082\u00d1\u008c \u00d0\u00bd\u00d0\u00b0\u00d0\u00bc"
      }
    ],
    "external_links": [],
    "images": [],
    "structured_data": [
      {
        "@context": "https://schema.org",
        "@graph": [
          {
            "@id": "https://rheolab.site/#organization",
            "@type": "Organization",
            "name": "RheoLab",
            "url": "https://rheolab.site/",
            "email": "info@rheolab.site",
            "description": "RheoLab \u00d1\u0080\u00d0\u00b0\u00d0\u00b7\u00d1\u0080\u00d0\u00b0\u00d0\u00b1\u00d0\u00b0\u00d1\u0082\u00d1\u008b\u00d0\u00b2\u00d0\u00b0\u00d0\u00b5\u00d1\u0082 RheoLab Enterprise \u00e2\u0080\u0094 Windows-\u00d0\u00bf\u00d1\u0080\u00d0\u00be\u00d0\u00b3\u00d1\u0080\u00d0\u00b0\u00d0\u00bc\u00d0\u00bc\u00d1\u0083 \u00d0\u00b4\u00d0\u00bb\u00d1\u008f \u00d1\u0085\u00d1\u0080\u00d0\u00b0\u00d0\u00bd\u00d0\u00b5\u00d0\u00bd\u00d0\u00b8\u00d1\u008f, \u00d1\u0081\u00d1\u0080\u00d0\u00b0\u00d0\u00b2\u00d0\u00bd\u00d0\u00b5\u00d0\u00bd\u00d0\u00b8\u00d1\u008f \u00d0\u00b8 \u00d0\u00bf\u00d0\u00be\u00d0\u00b4\u00d0\u00b3\u00d0\u00be\u00d1\u0082\u00d0\u00be\u00d0\u00b2\u00d0\u00ba\u00d0\u00b8 \u00d0\u00be\u00d1\u0082\u00d1\u0087\u00d1\u0091\u00d1\u0082\u00d0\u00be\u00d0\u00b2 \u00d0\u00bf\u00d0\u00be \u00d1\u0080\u00d0\u00b5\u00d0\u00b7\u00d1\u0083\u00d0\u00bb\u00d1\u008c\u00d1\u0082\u00d0\u00b0\u00d1\u0082\u00d0\u00b0\u00d0\u00bc \u00d1\u0080\u00d0\u00b5\u00d0\u00be\u00d0\u00bb\u00d0\u00be\u00d0\u00b3\u00d0\u00b8\u00d1\u0087\u00d0\u00b5\u00d1\u0081\u00d0\u00ba\u00d0\u00b8\u00d1\u0085 \u00d1\u008d\u00d0\u00ba\u00d1\u0081\u00d0\u00bf\u00d0\u00b5\u00d1\u0080\u00d0\u00b8\u00d0\u00bc\u00d0\u00b5\u00d0\u00bd\u00d1\u0082\u00d0\u00be\u00d0\u00b2.",
            "logo": "https://rheolab.site/favicon.svg",
            "contactPoint": [
              {
                "@type": "ContactPoint",
                "contactType": "sales",
                "email": "info@rheolab.site",
                "availableLanguage": [
                  "ru",
                  "en"
                ]
              },
              {
                "@type": "ContactPoint",
                "contactType": "technical support",
                "email": "support@rheolab.site",
                "availableLanguage": [
                  "ru",
                  "en"
                ]
              }
            ],
            "knowsAbout": [
              "Rheology software",
              "Laboratory data management",
              "Rheological experiment reports",
              "Instrument data import"
            ]
          },
          {
            "@id": "https://rheolab.site/#website",
            "@type": "WebSite",
            "name": "RheoLab Enterprise",
            "url": "https://rheolab.site/",
            "inLanguage": "ru-RU",
            "description": "\u00d0\u009e\u00d1\u0084\u00d0\u00b8\u00d1\u0086\u00d0\u00b8\u00d0\u00b0\u00d0\u00bb\u00d1\u008c\u00d0\u00bd\u00d1\u008b\u00d0\u00b9 \u00d1\u0081\u00d0\u00b0\u00d0\u00b9\u00d1\u0082 RheoLab Enterprise \u00d1\u0081 \u00d0\u00be\u00d0\u00bf\u00d0\u00b8\u00d1\u0081\u00d0\u00b0\u00d0\u00bd\u00d0\u00b8\u00d0\u00b5\u00d0\u00bc \u00d0\u00bf\u00d1\u0080\u00d0\u00be\u00d0\u00b4\u00d1\u0083\u00d0\u00ba\u00d1\u0082\u00d0\u00b0, \u00d0\u00b4\u00d0\u00be\u00d0\u00ba\u00d1\u0083\u00d0\u00bc\u00d0\u00b5\u00d0\u00bd\u00d1\u0082\u00d0\u00b0\u00d1\u0086\u00d0\u00b8\u00d0\u00b5\u00d0\u00b9, FAQ \u00d0\u00b8 \u00d0\u00ba\u00d0\u00be\u00d0\u00bd\u00d1\u0082\u00d0\u00b0\u00d0\u00ba\u00d1\u0082\u00d0\u00b0\u00d0\u00bc\u00d0\u00b8 \u00d0\u00ba\u00d0\u00be\u00d0\u00bc\u00d0\u00b0\u00d0\u00bd\u00d0\u00b4\u00d1\u008b.",
            "publisher": {
              "@id": "https://rheolab.site/#organization"
            }
          },
          {
            "@id": "https://rheolab.site/#software",
            "@type": "SoftwareApplication",
            "name": "RheoLab Enterprise",
            "applicationCategory": "BusinessApplication",
            "operatingSystem": "Windows 10, Windows 11",
            "description": "RheoLab Enterprise \u00e2\u0080\u0094 \u00d0\u00bf\u00d1\u0080\u00d0\u00be\u00d0\u00b3\u00d1\u0080\u00d0\u00b0\u00d0\u00bc\u00d0\u00bc\u00d0\u00b0 \u00d0\u00b4\u00d0\u00bb\u00d1\u008f \u00d1\u0085\u00d1\u0080\u00d0\u00b0\u00d0\u00bd\u00d0\u00b5\u00d0\u00bd\u00d0\u00b8\u00d1\u008f, \u00d1\u0081\u00d1\u0080\u00d0\u00b0\u00d0\u00b2\u00d0\u00bd\u00d0\u00b5\u00d0\u00bd\u00d0\u00b8\u00d1\u008f \u00d0\u00b8 \u00d0\u00bf\u00d0\u00be\u00d0\u00b4\u00d0\u00b3\u00d0\u00be\u00d1\u0082\u00d0\u00be\u00d0\u00b2\u00d0\u00ba\u00d0\u00b8 \u00d0\u00be\u00d1\u0082\u00d1\u0087\u00d1\u0091\u00d1\u0082\u00d0\u00be\u00d0\u00b2 \u00d0\u00bf\u00d0\u00be \u00d1\u0080\u00d0\u00b5\u00d0\u00b7\u00d1\u0083\u00d0\u00bb\u00d1\u008c\u00d1\u0082\u00d0\u00b0\u00d1\u0082\u00d0\u00b0\u00d0\u00bc \u00d1\u0080\u00d0\u00b5\u00d0\u00be\u00d0\u00bb\u00d0\u00be\u00d0\u00b3\u00d0\u00b8\u00d1\u0087\u00d0\u00b5\u00d1\u0081\u00d0\u00ba\u00d0\u00b8\u00d1\u0085 \u00d1\u008d\u00d0\u00ba\u00d1\u0081\u00d0\u00bf\u00d0\u00b5\u00d1\u0080\u00d0\u00b8\u00d0\u00bc\u00d0\u00b5\u00d0\u00bd\u00d1\u0082\u00d0\u00be\u00d0\u00b2 \u00d1\u0081 \u00d1\u0080\u00d0\u00b0\u00d0\u00b7\u00d0\u00bd\u00d1\u008b\u00d1\u0085 \u00d0\u00bf\u00d1\u0080\u00d0\u00b8\u00d0\u00b1\u00d0\u00be\u00d1\u0080\u00d0\u00be\u00d0\u00b2.",
            "url": "https://rheolab.site/",
            "downloadUrl": "https://rheolab.site/download/latest/",
            "inLanguage": "ru-RU",
            "publisher": {
              "@id": "https://rheolab.site/#organization"
            },
            "featureList": [
              "\u00d0\u0098\u00d0\u00bc\u00d0\u00bf\u00d0\u00be\u00d1\u0080\u00d1\u0082 \u00d0\u00b4\u00d0\u00b0\u00d0\u00bd\u00d0\u00bd\u00d1\u008b\u00d1\u0085 \u00d1\u0081 \u00d0\u00bb\u00d0\u00b0\u00d0\u00b1\u00d0\u00be\u00d1\u0080\u00d0\u00b0\u00d1\u0082\u00d0\u00be\u00d1\u0080\u00d0\u00bd\u00d1\u008b\u00d1\u0085 \u00d0\u00bf\u00d1\u0080\u00d0\u00b8\u00d0\u00b1\u00d0\u00be\u00d1\u0080\u00d0\u00be\u00d0\u00b2",
              "\u00d0\u009b\u00d0\u00be\u00d0\u00ba\u00d0\u00b0\u00d0\u00bb\u00d1\u008c\u00d0\u00bd\u00d0\u00be\u00d0\u00b5 \u00d1\u0085\u00d1\u0080\u00d0\u00b0\u00d0\u00bd\u00d0\u00b5\u00d0\u00bd\u00d0\u00b8\u00d0\u00b5 \u00d1\u0080\u00d0\u00b5\u00d0\u00b7\u00d1\u0083\u00d0\u00bb\u00d1\u008c\u00d1\u0082\u00d0\u00b0\u00d1\u0082\u00d0\u00be\u00d0\u00b2 \u00d1\u008d\u00d0\u00ba\u00d1\u0081\u00d0\u00bf\u00d0\u00b5\u00d1\u0080\u00d0\u00b8\u00d0\u00bc\u00d0\u00b5\u00d0\u00bd\u00d1\u0082\u00d0\u00be\u00d0\u00b2",
              "\u00d0\u00a1\u00d1\u0080\u00d0\u00b0\u00d0\u00b2\u00d0\u00bd\u00d0\u00b5\u00d0\u00bd\u00d0\u00b8\u00d0\u00b5 \u00d1\u0081\u00d0\u00b5\u00d1\u0080\u00d0\u00b8\u00d0\u00b9 \u00d0\u00b8 \u00d1\u0080\u00d0\u00b0\u00d1\u0081\u00d1\u0087\u00d1\u0091\u00d1\u0082\u00d0\u00bd\u00d1\u008b\u00d1\u0085 \u00d0\u00bc\u00d0\u00be\u00d0\u00b4\u00d0\u00b5\u00d0\u00bb\u00d0\u00b5\u00d0\u00b9",
              "\u00d0\u009f\u00d0\u00be\u00d0\u00b4\u00d0\u00b3\u00d0\u00be\u00d1\u0082\u00d0\u00be\u00d0\u00b2\u00d0\u00ba\u00d0\u00b0 PDF- \u00d0\u00b8 Excel-\u00d0\u00be\u00d1\u0082\u00d1\u0087\u00d1\u0091\u00d1\u0082\u00d0\u00be\u00d0\u00b2"
            ]
          },
          {
            "@type": "WebPage",
            "name": "RheoLab Enterprise",
            "description": "RheoLab Enterprise \u00e2\u0080\u0094 \u00d0\u00bf\u00d1\u0080\u00d0\u00be\u00d0\u00b3\u00d1\u0080\u00d0\u00b0\u00d0\u00bc\u00d0\u00bc\u00d0\u00b0 \u00d0\u00b4\u00d0\u00bb\u00d1\u008f \u00d1\u0085\u00d1\u0080\u00d0\u00b0\u00d0\u00bd\u00d0\u00b5\u00d0\u00bd\u00d0\u00b8\u00d1\u008f, \u00d1\u0081\u00d1\u0080\u00d0\u00b0\u00d0\u00b2\u00d0\u00bd\u00d0\u00b5\u00d0\u00bd\u00d0\u00b8\u00d1\u008f \u00d0\u00b8 \u00d0\u00bf\u00d0\u00be\u00d0\u00b4\u00d0\u00b3\u00d0\u00be\u00d1\u0082\u00d0\u00be\u00d0\u00b2\u00d0\u00ba\u00d0\u00b8 \u00d0\u00be\u00d1\u0082\u00d1\u0087\u00d1\u0091\u00d1\u0082\u00d0\u00be\u00d0\u00b2 \u00d0\u00bf\u00d0\u00be \u00d1\u0080\u00d0\u00b5\u00d0\u00b7\u00d1\u0083\u00d0\u00bb\u00d1\u008c\u00d1\u0082\u00d0\u00b0\u00d1\u0082\u00d0\u00b0\u00d0\u00bc \u00d1\u0080\u00d0\u00b5\u00d0\u00be\u00d0\u00bb\u00d0\u00be\u00d0\u00b3\u00d0\u00b8\u00d1\u0087\u00d0\u00b5\u00d1\u0081\u00d0\u00ba\u00d0\u00b8\u00d1\u0085 \u00d1\u008d\u00d0\u00ba\u00d1\u0081\u00d0\u00bf\u00d0\u00b5\u00d1\u0080\u00d0\u00b8\u00d0\u00bc\u00d0\u00b5\u00d0\u00bd\u00d1\u0082\u00d0\u00be\u00d0\u00b2 \u00d1\u0081 \u00d1\u0080\u00d0\u00b0\u00d0\u00b7\u00d0\u00bd\u00d1\u008b\u00d1\u0085 \u00d0\u00bf\u00d1\u0080\u00d0\u00b8\u00d0\u00b1\u00d0\u00be\u00d1\u0080\u00d0\u00be\u00d0\u00b2.",
            "url": "https://rheolab.site/",
            "inLanguage": "ru-RU",
            "dateModified": "2026-04-12"
          }
        ]
      }
    ],
    "has_ssr_content": true,
    "security_headers": {
      "Strict-Transport-Security": "max-age=31536000; includeSubDomains; preload",
      "Content-Security-Policy": "default-src 'self'; base-uri 'self'; object-src 'none'; frame-ancestors 'none'; form-action 'self'; img-src 'self' data: https:; style-src 'self' 'unsafe-inline' https://fonts.googleapis.com; font-src 'self' data: https://fonts.gstatic.com; script-src 'self' 'unsafe-inline'; connect-src 'self' https://license.vizbuka.ru; upgrade-insecure-requests",
      "X-Frame-Options": "DENY",
      "X-Content-Type-Options": "nosniff",
      "Referrer-Policy": "strict-origin-when-cross-origin",
      "Permissions-Policy": "accelerometer=(), autoplay=(), camera=(), geolocation=(), gyroscope=(), magnetometer=(), microphone=(), payment=(), usb=(), browsing-topics=()"
    },
    "errors": []
  },
  "robots": {
    "url": "https://rheolab.site/robots.txt",
    "exists": true,
    "content": "User-agent: *\nAllow: /\n\nSitemap: https://rheolab.site/sitemap-index.xml\n",
    "ai_crawler_status": {
      "GPTBot": "ALLOWED_BY_DEFAULT",
      "OAI-SearchBot": "ALLOWED_BY_DEFAULT",
      "ChatGPT-User": "ALLOWED_BY_DEFAULT",
      "ClaudeBot": "ALLOWED_BY_DEFAULT",
      "anthropic-ai": "ALLOWED_BY_DEFAULT",
      "PerplexityBot": "ALLOWED_BY_DEFAULT",
      "CCBot": "ALLOWED_BY_DEFAULT",
      "Bytespider": "ALLOWED_BY_DEFAULT",
      "cohere-ai": "ALLOWED_BY_DEFAULT",
      "Google-Extended": "ALLOWED_BY_DEFAULT",
      "GoogleOther": "ALLOWED_BY_DEFAULT",
      "Applebot-Extended": "ALLOWED_BY_DEFAULT",
      "FacebookBot": "ALLOWED_BY_DEFAULT",
      "Amazonbot": "ALLOWED_BY_DEFAULT"
    },
    "sitemaps": [
      "https://rheolab.site/sitemap-index.xml"
    ],
    "errors": []
  },
  "llms": {
    "llms_txt": {
      "url": "https://rheolab.site/llms.txt",
      "exists": true,
      "content": "# RheoLab Enterprise\n> RheoLab Enterprise is a Windows desktop application for storing, comparing, and reporting rheology experiment results from multiple laboratory instruments. Primary website language: Russian.\n\n## Primary Pages\n- [Home](https://rheolab.site/): Product overview, workflows, supported use cases, and contact entry points.\n- [FAQ](https://rheolab.site/faq/): Licensing, trial, storage, supported instruments, and deployment questions.\n- [Download](https://rheolab.site/download/latest/): Redirector to the latest Windows installer.\n- [Privacy](https://rheolab.site/privacy/): Privacy and data-handling policy.\n- [Terms](https://rheolab.site/terms/): Terms of use and licensing conditions.\n\n## Documentation\n- [Documentation Index](https://rheolab.site/docs/): Main entry point to the product documentation.\n- [Quick Start](https://rheolab.site/docs/quick-start/): Install the software, start the trial, open the first file, and save the first result.\n- [Data Import](https://rheolab.site/docs/parsing/): Supported file formats and instrument families.\n- [Interface](https://rheolab.site/docs/interface/): Main application areas and navigation.\n- [Calculation Models](https://rheolab.site/docs/models/): Rheology models and calculated parameters.\n- [Reports](https://rheolab.site/docs/reports/): PDF and Excel reporting workflow.\n- [Troubleshooting](https://rheolab.site/docs/troubleshooting/): Installation, launch, and import troubleshooting.\n- [Documentation FAQ](https://rheolab.site/docs/faq/): Short answers for common evaluation and usage questions.\n\n## Contact\n- [Commercial Contact](mailto:info@rheolab.site): Product demos, licensing, and rollout questions.\n- [Technical Support](mailto:support@rheolab.site): Installation, import, backup, and troubleshooting questions.\n\n## Optional\n- [llms-full.txt](https://rheolab.site/llms-full.txt): Expanded machine-readable summary of the site, product facts, and documentation map.\n"
    },
    "llms_full_txt": {
      "url": "https://rheolab.site/llms-full.txt",
      "exists": true,
      "content": "# RheoLab Enterprise\n> RheoLab Enterprise is a Windows desktop application for laboratory teams and technical specialists working with rheology experiment data. The product focuses on local-first storage, comparison of experiment series, and report preparation. Primary website language: Russian.\n\n## Product Facts\n- Product type: Windows desktop software for rheology data workflows.\n- Core workflow: import a file, review the graph and calculated values, save the result to the library, compare series, and export reports.\n- Storage model: the public site states that experiment data is stored locally on the user's computer.\n- Trial: a 30-day full-feature trial is available.\n- Connectivity: daily work is local-first; internet is mainly required for activation, updates, and some additional network-assisted scenarios.\n\n## Supported Inputs Mentioned Publicly\n- Instrument families: Grace, Chandler, Fann, OFITE, BSL-R1, Brookfield.\n- File formats: `.xls`, `.xlsx`, `.csv`, `.txt`, `.dat`.\n\n## Primary Audience\n- Laboratory teams working with rheology measurements.\n- Engineering and technical departments handling experiment series.\n- Researchers and lab managers who need a structured result library and repeatable reporting.\n\n## High-Value Pages\n- [Home](https://rheolab.site/): Main product overview and contact path.\n- [FAQ](https://rheolab.site/faq/): Public FAQ covering trial, licensing, file formats, instrument support, local storage, and deployment context.\n- [Download](https://rheolab.site/download/latest/): Latest Windows installer redirect.\n- [Privacy](https://rheolab.site/privacy/): Privacy commitments, local data handling, and support/log submission notes.\n- [Terms](https://rheolab.site/terms/): License types, restrictions, user data responsibility, and legal contacts.\n\n## Documentation Map\n### Start Here\n- [Documentation Index](https://rheolab.site/docs/): Documentation hub.\n- [Quick Start](https://rheolab.site/docs/quick-start/): Installation, trial activation, first import, and first saved result.\n\n### Operational Help\n- [Documentation FAQ](https://rheolab.site/docs/faq/): Short answers to common evaluation and usage questions.\n- [Troubleshooting](https://rheolab.site/docs/troubleshooting/): Install, launch, white screen, data, and logging issues.\n\n### Product Workflows\n- [Data Import](https://rheolab.site/docs/parsing/): File formats, source instruments, and import failure guidance.\n- [Interface](https://rheolab.site/docs/interface/): Main areas of the application and the shortest learning path.\n- [Reports](https://rheolab.site/docs/reports/): PDF and Excel reporting flow.\n\n### Domain-Specific Reference\n- [Calculation Models](https://rheolab.site/docs/models/): Power Law, Bingham, and reference notes around model calculations and parameters.\n\n## Contact Endpoints\n- [Commercial Contact](mailto:info@rheolab.site): Product demos, licensing, and deployment planning.\n- [Technical Support](mailto:support@rheolab.site): Setup, import, backup, and troubleshooting.\n- [Privacy Contact](mailto:privacy@rheolab.site): Privacy questions.\n- [Legal Contact](mailto:legal@rheolab.site): Legal questions.\n"
    },
    "errors": []
  },
  "sitemap": []
}
